{"pagination":{"countCurrent":20,"countTotal":17965,"pageCurrent":62,"pageTotal":899,"itemsPerPage":20},"items":[{"id":16931,"resourceId":67335093,"resourceBaseId":226229,"futBinId":50311,"futWizId":19172,"firstName":"Thilo","lastName":"Kehrer","name":"Thilo Kehrer","commonName":"Kehrer","height":186,"weight":76,"birthDate":"1996-09-21","age":26,"league":13,"nation":21,"club":19,"rarity":146,"traits":[],"specialities":[],"position":"CB","skillMoves":3,"weakFoot":5,"foot":"Right","attackWorkRate":"Med","defenseWorkRate":"Med","totalStats":461,"totalStatsInGame":2158,"color":"gold","rating":85,"ratingAverage":76,"pace":84,"shooting":50,"passing":77,"dribbling":78,"defending":85,"physicality":87,"paceAttributes":{"acceleration":81,"sprintSpeed":86},"shootingAttributes":{"positioning":60,"finishing":42,"shotPower":74,"longShots":45,"volleys":36,"penalties":47},"passingAttributes":{"vision":72,"crossing":76,"freeKickAccuracy":46,"shortPassing":86,"longPassing":80,"curve":67},"dribblingAttributes":{"agility":80,"balance":76,"reactions":86,"ballControl":80,"dribbling":76,"composure":82},"defendingAttributes":{"interceptions":85,"headingAccuracy":82,"standingTackle":87,"slidingTackle":88,"defenseAwareness":84},"physicalityAttributes":{"jumping":96,"stamina":81,"strength":90,"aggression":87},"goalkeeperAttributes":{"diving":null,"handling":null,"kicking":null,"positioning":null,"reflexes":null,"speed":83}},{"id":16956,"resourceId":67345628,"resourceBaseId":236764,"futBinId":50321,"futWizId":19181,"firstName":"Ao","lastName":"Tanaka","name":"Ao Tanaka","commonName":"Tanaka","height":177,"weight":69,"birthDate":"1998-09-10","age":24,"league":20,"nation":163,"club":110636,"rarity":150,"traits":[],"specialities":[],"position":"CDM","skillMoves":3,"weakFoot":3,"foot":"Right","attackWorkRate":"Med","defenseWorkRate":"Med","totalStats":490,"totalStatsInGame":2340,"color":"gold","rating":85,"ratingAverage":81,"pace":81,"shooting":78,"passing":82,"dribbling":84,"defending":82,"physicality":83,"paceAttributes":{"acceleration":87,"sprintSpeed":76},"shootingAttributes":{"positioning":76,"finishing":78,"shotPower":84,"longShots":80,"volleys":66,"penalties":66},"passingAttributes":{"vision":81,"crossing":74,"freeKickAccuracy":78,"shortPassing":87,"longPassing":87,"curve":76},"dribblingAttributes":{"agility":96,"balance":90,"reactions":83,"ballControl":86,"dribbling":80,"composure":83},"defendingAttributes":{"interceptions":81,"headingAccuracy":63,"standingTackle":87,"slidingTackle":80,"defenseAwareness":84},"physicalityAttributes":{"jumping":76,"stamina":94,"strength":77,"aggression":84},"goalkeeperAttributes":{"diving":null,"handling":null,"kicking":null,"positioning":null,"reflexes":null,"speed":81}},{"id":16957,"resourceId":84127855,"resourceBaseId":241775,"futBinId":50320,"futWizId":19180,"firstName":"Jawad","lastName":"El Yamiq","name":"Jawad El Yamiq","commonName":"El Yamiq","height":193,"weight":80,"birthDate":"1992-02-29","age":31,"league":53,"nation":129,"club":462,"rarity":150,"traits":[{"id":7,"name":"Long Passer (CPU AI)"},{"id":10,"name":"Long Shot Taker (CPU AI)"},{"id":13,"name":"Dives Into Tackles (CPU AI)"},{"id":21,"name":"Injury Prone"}],"specialities":[],"position":"CB","skillMoves":2,"weakFoot":3,"foot":"Right","attackWorkRate":"Med","defenseWorkRate":"Med","totalStats":442,"totalStatsInGame":2028,"color":"gold","rating":85,"ratingAverage":73,"pace":88,"shooting":57,"passing":60,"dribbling":69,"defending":81,"physicality":87,"paceAttributes":{"acceleration":86,"sprintSpeed":89},"shootingAttributes":{"positioning":71,"finishing":48,"shotPower":79,"longShots":61,"volleys":35,"penalties":48},"passingAttributes":{"vision":43,"crossing":44,"freeKickAccuracy":37,"shortPassing":75,"longPassing":82,"curve":42},"dribblingAttributes":{"agility":77,"balance":62,"reactions":81,"ballControl":68,"dribbling":67,"composure":76},"defendingAttributes":{"interceptions":84,"headingAccuracy":83,"standingTackle":82,"slidingTackle":77,"defenseAwareness":80},"physicalityAttributes":{"jumping":98,"stamina":82,"strength":91,"aggression":80},"goalkeeperAttributes":{"diving":null,"handling":null,"kicking":null,"positioning":null,"reflexes":null,"speed":87}},{"id":16970,"resourceId":67318753,"resourceBaseId":209889,"futBinId":50349,"futWizId":19207,"firstName":"Raphaël","lastName":"Guerreiro","name":"Guerreiro","commonName":"Guerreiro","height":170,"weight":71,"birthDate":"1993-12-22","age":29,"league":19,"nation":38,"club":22,"rarity":138,"traits":[{"id":1,"name":"Technical Dribbler (CPU AI)"},{"id":8,"name":"Flair"},{"id":9,"name":"Outside Foot Shot"},{"id":21,"name":"Injury Prone"}],"specialities":[],"position":"LB","skillMoves":4,"weakFoot":3,"foot":"Left","attackWorkRate":"High","defenseWorkRate":"High","totalStats":501,"totalStatsInGame":2404,"color":"gold","rating":85,"ratingAverage":83,"pace":85,"shooting":80,"passing":91,"dribbling":90,"defending":82,"physicality":73,"paceAttributes":{"acceleration":95,"sprintSpeed":77},"shootingAttributes":{"positioning":82,"finishing":80,"shotPower":81,"longShots":83,"volleys":82,"penalties":56},"passingAttributes":{"vision":90,"crossing":91,"freeKickAccuracy":87,"shortPassing":93,"longPassing":90,"curve":90},"dribblingAttributes":{"agility":93,"balance":93,"reactions":89,"ballControl":90,"dribbling":90,"composure":89},"defendingAttributes":{"interceptions":91,"headingAccuracy":48,"standingTackle":82,"slidingTackle":83,"defenseAwareness":86},"physicalityAttributes":{"jumping":69,"stamina":98,"strength":66,"aggression":60},"goalkeeperAttributes":{"diving":null,"handling":null,"kicking":null,"positioning":null,"reflexes":null,"speed":86}},{"id":16990,"resourceId":67341503,"resourceBaseId":232639,"futBinId":50353,"futWizId":19212,"firstName":"Ritsu","lastName":"Doan","name":"Ritsu Doan","commonName":"Doan","height":172,"weight":70,"birthDate":"1998-06-16","age":24,"league":19,"nation":163,"club":25,"rarity":138,"traits":[{"id":1,"name":"Technical Dribbler (CPU AI)"},{"id":9,"name":"Outside Foot Shot"}],"specialities":[],"position":"RM","skillMoves":4,"weakFoot":3,"foot":"Left","attackWorkRate":"Med","defenseWorkRate":"Med","totalStats":456,"totalStatsInGame":2153,"color":"gold","rating":85,"ratingAverage":76,"pace":90,"shooting":80,"passing":83,"dribbling":90,"defending":47,"physicality":66,"paceAttributes":{"acceleration":92,"sprintSpeed":89},"shootingAttributes":{"positioning":81,"finishing":79,"shotPower":86,"longShots":85,"volleys":66,"penalties":65},"passingAttributes":{"vision":88,"crossing":82,"freeKickAccuracy":76,"shortPassing":85,"longPassing":78,"curve":84},"dribblingAttributes":{"agility":96,"balance":99,"reactions":83,"ballControl":89,"dribbling":89,"composure":82},"defendingAttributes":{"interceptions":52,"headingAccuracy":53,"standingTackle":42,"slidingTackle":49,"defenseAwareness":46},"physicalityAttributes":{"jumping":38,"stamina":87,"strength":66,"aggression":46},"goalkeeperAttributes":{"diving":null,"handling":null,"kicking":null,"positioning":null,"reflexes":null,"speed":90}},{"id":17039,"resourceId":100915150,"resourceBaseId":251854,"futBinId":50414,"futWizId":19270,"firstName":"Pedro","lastName":"González López","name":"Pedri","commonName":"Pedri","height":174,"weight":61,"birthDate":"2002-11-25","age":20,"league":53,"nation":45,"club":241,"rarity":156,"traits":[{"id":1,"name":"Technical Dribbler (CPU AI)"},{"id":4,"name":"Solid Player"},{"id":8,"name":"Flair"}],"specialities":[],"position":"CM","skillMoves":4,"weakFoot":4,"foot":"Right","attackWorkRate":"High","defenseWorkRate":"High","totalStats":467,"totalStatsInGame":2208,"color":"gold","rating":85,"ratingAverage":75,"pace":79,"shooting":67,"passing":81,"dribbling":87,"defending":68,"physicality":73,"paceAttributes":{"acceleration":84,"sprintSpeed":78},"shootingAttributes":{"positioning":79,"finishing":70,"shotPower":68,"longShots":69,"volleys":58,"penalties":55},"passingAttributes":{"vision":90,"crossing":70,"freeKickAccuracy":64,"shortPassing":89,"longPassing":87,"curve":81},"dribblingAttributes":{"agility":90,"balance":92,"reactions":87,"ballControl":90,"dribbling":89,"composure":89},"defendingAttributes":{"interceptions":74,"headingAccuracy":52,"standingTackle":75,"slidingTackle":65,"defenseAwareness":70},"physicalityAttributes":{"jumping":67,"stamina":90,"strength":72,"aggression":64},"goalkeeperAttributes":{"diving":null,"handling":null,"kicking":null,"positioning":null,"reflexes":null,"speed":81}},{"id":17043,"resourceId":50501345,"resourceBaseId":169697,"futBinId":50410,"futWizId":19269,"firstName":"Darren","lastName":"Randolph","name":"Darren Randolph","commonName":"Randolph","height":188,"weight":78,"birthDate":"1987-05-12","age":35,"league":13,"nation":25,"club":19,"rarity":118,"traits":[{"id":12,"name":"Team Player"},{"id":18,"name":"Comes for Crosses"}],"specialities":[],"position":"GK","skillMoves":5,"weakFoot":5,"foot":"Right","attackWorkRate":"Med","defenseWorkRate":"Med","totalStats":488,"totalStatsInGame":884,"color":"gold","rating":85,"ratingAverage":81,"pace":0,"shooting":0,"passing":0,"dribbling":0,"defending":0,"physicality":0,"paceAttributes":{"acceleration":null,"sprintSpeed":null},"shootingAttributes":{"positioning":null,"finishing":null,"shotPower":null,"longShots":null,"volleys":null,"penalties":null},"passingAttributes":{"vision":null,"crossing":null,"freeKickAccuracy":null,"shortPassing":null,"longPassing":null,"curve":null},"dribblingAttributes":{"agility":null,"balance":null,"reactions":null,"ballControl":null,"dribbling":null,"composure":36},"defendingAttributes":{"interceptions":null,"headingAccuracy":null,"standingTackle":null,"slidingTackle":null,"defenseAwareness":null},"physicalityAttributes":{"jumping":null,"stamina":null,"strength":null,"aggression":null},"goalkeeperAttributes":{"diving":86,"handling":84,"kicking":99,"positioning":84,"reflexes":85,"speed":50}},{"id":17044,"resourceId":50586192,"resourceBaseId":254544,"futBinId":50408,"futWizId":19266,"firstName":"Reinier","lastName":"Jesus Carvalho","name":"Reinier Jesus Carvalho","commonName":"Reinier","height":185,"weight":82,"birthDate":"2002-01-19","age":21,"league":53,"nation":54,"club":110062,"rarity":118,"traits":[{"id":1,"name":"Technical Dribbler (CPU AI)"},{"id":8,"name":"Flair"}],"specialities":[],"position":"CAM","skillMoves":4,"weakFoot":4,"foot":"Right","attackWorkRate":"Med","defenseWorkRate":"Med","totalStats":458,"totalStatsInGame":2188,"color":"gold","rating":85,"ratingAverage":76,"pace":85,"shooting":84,"passing":83,"dribbling":86,"defending":45,"physicality":75,"paceAttributes":{"acceleration":86,"sprintSpeed":84},"shootingAttributes":{"positioning":84,"finishing":85,"shotPower":88,"longShots":80,"volleys":87,"penalties":81},"passingAttributes":{"vision":81,"crossing":77,"freeKickAccuracy":70,"shortPassing":89,"longPassing":80,"curve":90},"dribblingAttributes":{"agility":88,"balance":85,"reactions":80,"ballControl":85,"dribbling":88,"composure":84},"defendingAttributes":{"interceptions":32,"headingAccuracy":62,"standingTackle":49,"slidingTackle":42,"defenseAwareness":44},"physicalityAttributes":{"jumping":62,"stamina":80,"strength":76,"aggression":69},"goalkeeperAttributes":{"diving":null,"handling":null,"kicking":null,"positioning":null,"reflexes":null,"speed":85}},{"id":17045,"resourceId":50557492,"resourceBaseId":225844,"futBinId":50407,"futWizId":19267,"firstName":"Daniele","lastName":"Verde","name":"Daniele Verde","commonName":"Verde","height":168,"weight":64,"birthDate":"1996-06-20","age":26,"league":31,"nation":27,"club":113974,"rarity":118,"traits":[{"id":1,"name":"Technical Dribbler (CPU AI)"},{"id":8,"name":"Flair"},{"id":10,"name":"Long Shot Taker (CPU AI)"},{"id":11,"name":"Power Free-Kick"}],"specialities":[],"position":"RW","skillMoves":4,"weakFoot":3,"foot":"Left","attackWorkRate":"Med","defenseWorkRate":"Low","totalStats":452,"totalStatsInGame":2202,"color":"gold","rating":85,"ratingAverage":75,"pace":90,"shooting":84,"passing":99,"dribbling":85,"defending":39,"physicality":55,"paceAttributes":{"acceleration":90,"sprintSpeed":90},"shootingAttributes":{"positioning":84,"finishing":85,"shotPower":86,"longShots":87,"volleys":67,"penalties":80},"passingAttributes":{"vision":99,"crossing":99,"freeKickAccuracy":99,"shortPassing":99,"longPassing":96,"curve":99},"dribblingAttributes":{"agility":95,"balance":98,"reactions":78,"ballControl":83,"dribbling":83,"composure":80},"defendingAttributes":{"interceptions":26,"headingAccuracy":50,"standingTackle":40,"slidingTackle":38,"defenseAwareness":44},"physicalityAttributes":{"jumping":43,"stamina":83,"strength":40,"aggression":61},"goalkeeperAttributes":{"diving":null,"handling":null,"kicking":null,"positioning":null,"reflexes":null,"speed":90}},{"id":17046,"resourceId":100902389,"resourceBaseId":239093,"futBinId":50406,"futWizId":19268,"firstName":"Jonathan","lastName":"Clauss","name":"Jonathan Clauss","commonName":"Clauss","height":178,"weight":69,"birthDate":"1992-09-25","age":30,"league":16,"nation":18,"club":219,"rarity":118,"traits":[{"id":15,"name":"Early Crosser"}],"specialities":[],"position":"RWB","skillMoves":3,"weakFoot":3,"foot":"Right","attackWorkRate":"High","defenseWorkRate":"High","totalStats":500,"totalStatsInGame":2382,"color":"gold","rating":85,"ratingAverage":83,"pace":89,"shooting":75,"passing":99,"dribbling":83,"defending":77,"physicality":77,"paceAttributes":{"acceleration":90,"sprintSpeed":88},"shootingAttributes":{"positioning":82,"finishing":74,"shotPower":84,"longShots":74,"volleys":61,"penalties":57},"passingAttributes":{"vision":99,"crossing":99,"freeKickAccuracy":99,"shortPassing":99,"longPassing":99,"curve":99},"dribblingAttributes":{"agility":88,"balance":74,"reactions":83,"ballControl":83,"dribbling":82,"composure":81},"defendingAttributes":{"interceptions":77,"headingAccuracy":64,"standingTackle":84,"slidingTackle":79,"defenseAwareness":75},"physicalityAttributes":{"jumping":68,"stamina":97,"strength":69,"aggression":74},"goalkeeperAttributes":{"diving":null,"handling":null,"kicking":null,"positioning":null,"reflexes":null,"speed":89}},{"id":17064,"resourceId":50532767,"resourceBaseId":201119,"futBinId":50440,"futWizId":19285,"firstName":"Ismaily","lastName":"Gonçalves dos S.","name":"Ismaily","commonName":"Ismaily","height":177,"weight":82,"birthDate":"1990-01-11","age":33,"league":16,"nation":54,"club":65,"rarity":118,"traits":[{"id":1,"name":"Technical Dribbler (CPU AI)"},{"id":8,"name":"Flair"}],"specialities":[],"position":"LB","skillMoves":4,"weakFoot":3,"foot":"Left","attackWorkRate":"High","defenseWorkRate":"Med","totalStats":489,"totalStatsInGame":2265,"color":"gold","rating":85,"ratingAverage":81,"pace":89,"shooting":70,"passing":80,"dribbling":84,"defending":83,"physicality":83,"paceAttributes":{"acceleration":91,"sprintSpeed":87},"shootingAttributes":{"positioning":90,"finishing":66,"shotPower":82,"longShots":70,"volleys":59,"penalties":55},"passingAttributes":{"vision":75,"crossing":85,"freeKickAccuracy":54,"shortPassing":87,"longPassing":75,"curve":70},"dribblingAttributes":{"agility":77,"balance":86,"reactions":83,"ballControl":85,"dribbling":85,"composure":83},"defendingAttributes":{"interceptions":89,"headingAccuracy":65,"standingTackle":83,"slidingTackle":81,"defenseAwareness":84},"physicalityAttributes":{"jumping":72,"stamina":91,"strength":84,"aggression":71},"goalkeeperAttributes":{"diving":null,"handling":null,"kicking":null,"positioning":null,"reflexes":null,"speed":89}},{"id":17065,"resourceId":50544559,"resourceBaseId":212911,"futBinId":50439,"futWizId":19284,"firstName":"Hernâni Jorge","lastName":"Santos Fortes","name":"Hernâni","commonName":"Hernâni","height":179,"weight":73,"birthDate":"1991-08-20","age":31,"league":308,"nation":38,"club":744,"rarity":118,"traits":[{"id":6,"name":"Speed Dribbler (CPU AI)"},{"id":8,"name":"Flair"}],"specialities":[],"position":"RM","skillMoves":5,"weakFoot":3,"foot":"Left","attackWorkRate":"Med","defenseWorkRate":"Low","totalStats":446,"totalStatsInGame":2168,"color":"gold","rating":85,"ratingAverage":74,"pace":90,"shooting":84,"passing":81,"dribbling":86,"defending":35,"physicality":70,"paceAttributes":{"acceleration":90,"sprintSpeed":90},"shootingAttributes":{"positioning":87,"finishing":80,"shotPower":90,"longShots":84,"volleys":86,"penalties":88},"passingAttributes":{"vision":83,"crossing":81,"freeKickAccuracy":80,"shortPassing":80,"longPassing":78,"curve":88},"dribblingAttributes":{"agility":97,"balance":85,"reactions":78,"ballControl":81,"dribbling":89,"composure":81},"defendingAttributes":{"interceptions":25,"headingAccuracy":66,"standingTackle":23,"slidingTackle":28,"defenseAwareness":46},"physicalityAttributes":{"jumping":70,"stamina":85,"strength":66,"aggression":63},"goalkeeperAttributes":{"diving":null,"handling":null,"kicking":null,"positioning":null,"reflexes":null,"speed":90}},{"id":17072,"resourceId":50578705,"resourceBaseId":247057,"futBinId":50445,"futWizId":19290,"firstName":"Noble","lastName":"Okello","name":"Noble Okello","commonName":"Okello","height":196,"weight":93,"birthDate":"2000-07-20","age":22,"league":39,"nation":70,"club":111651,"rarity":118,"traits":[],"specialities":[],"position":"CDM","skillMoves":2,"weakFoot":4,"foot":"Right","attackWorkRate":"High","defenseWorkRate":"High","totalStats":491,"totalStatsInGame":2288,"color":"gold","rating":85,"ratingAverage":81,"pace":83,"shooting":76,"passing":80,"dribbling":84,"defending":82,"physicality":86,"paceAttributes":{"acceleration":78,"sprintSpeed":87},"shootingAttributes":{"positioning":85,"finishing":70,"shotPower":86,"longShots":80,"volleys":60,"penalties":84},"passingAttributes":{"vision":91,"crossing":50,"freeKickAccuracy":57,"shortPassing":92,"longPassing":91,"curve":57},"dribblingAttributes":{"agility":73,"balance":65,"reactions":80,"ballControl":87,"dribbling":87,"composure":83},"defendingAttributes":{"interceptions":81,"headingAccuracy":91,"standingTackle":82,"slidingTackle":80,"defenseAwareness":82},"physicalityAttributes":{"jumping":78,"stamina":83,"strength":93,"aggression":75},"goalkeeperAttributes":{"diving":null,"handling":null,"kicking":null,"positioning":null,"reflexes":null,"speed":82}},{"id":17075,"resourceId":50567115,"resourceBaseId":235467,"futBinId":50463,"futWizId":19307,"firstName":"Marcelino","lastName":"Moreno","name":"Marcelino Moreno","commonName":"Moreno","height":168,"weight":65,"birthDate":"1995-06-25","age":27,"league":39,"nation":52,"club":112885,"rarity":118,"traits":[{"id":1,"name":"Technical Dribbler (CPU AI)"},{"id":9,"name":"Outside Foot Shot"}],"specialities":[],"position":"CM","skillMoves":5,"weakFoot":3,"foot":"Right","attackWorkRate":"High","defenseWorkRate":"High","totalStats":485,"totalStatsInGame":2352,"color":"gold","rating":85,"ratingAverage":80,"pace":84,"shooting":82,"passing":85,"dribbling":88,"defending":72,"physicality":74,"paceAttributes":{"acceleration":87,"sprintSpeed":82},"shootingAttributes":{"positioning":86,"finishing":82,"shotPower":86,"longShots":83,"volleys":70,"penalties":76},"passingAttributes":{"vision":89,"crossing":80,"freeKickAccuracy":76,"shortPassing":86,"longPassing":88,"curve":90},"dribblingAttributes":{"agility":92,"balance":96,"reactions":85,"ballControl":86,"dribbling":87,"composure":86},"defendingAttributes":{"interceptions":78,"headingAccuracy":68,"standingTackle":72,"slidingTackle":70,"defenseAwareness":70},"physicalityAttributes":{"jumping":67,"stamina":95,"strength":63,"aggression":76},"goalkeeperAttributes":{"diving":null,"handling":null,"kicking":null,"positioning":null,"reflexes":null,"speed":84}},{"id":17091,"resourceId":84132020,"resourceBaseId":245940,"futBinId":50465,"futWizId":19309,"firstName":"Silas","lastName":"Katompa Mvumpa","name":"Silas","commonName":"Silas","height":189,"weight":82,"birthDate":"1998-10-06","age":24,"league":19,"nation":110,"club":36,"rarity":118,"traits":[{"id":1,"name":"Technical Dribbler (CPU AI)"},{"id":6,"name":"Speed Dribbler (CPU AI)"},{"id":8,"name":"Flair"},{"id":21,"name":"Injury Prone"}],"specialities":[],"position":"ST","skillMoves":5,"weakFoot":3,"foot":"Right","attackWorkRate":"High","defenseWorkRate":"Med","totalStats":484,"totalStatsInGame":2221,"color":"gold","rating":85,"ratingAverage":80,"pace":95,"shooting":85,"passing":78,"dribbling":88,"defending":60,"physicality":78,"paceAttributes":{"acceleration":93,"sprintSpeed":96},"shootingAttributes":{"positioning":91,"finishing":92,"shotPower":84,"longShots":72,"volleys":76,"penalties":90},"passingAttributes":{"vision":75,"crossing":84,"freeKickAccuracy":42,"shortPassing":90,"longPassing":61,"curve":75},"dribblingAttributes":{"agility":92,"balance":80,"reactions":77,"ballControl":85,"dribbling":92,"composure":76},"defendingAttributes":{"interceptions":62,"headingAccuracy":75,"standingTackle":58,"slidingTackle":45,"defenseAwareness":61},"physicalityAttributes":{"jumping":67,"stamina":83,"strength":81,"aggression":66},"goalkeeperAttributes":{"diving":null,"handling":null,"kicking":null,"positioning":null,"reflexes":null,"speed":94}},{"id":17092,"resourceId":67300604,"resourceBaseId":191740,"futBinId":50470,"futWizId":19313,"firstName":"Ander","lastName":"Herrera Agüera","name":"Ander Herrera","commonName":"Ander Herrera","height":182,"weight":71,"birthDate":"1989-08-14","age":33,"league":53,"nation":45,"club":448,"rarity":118,"traits":[{"id":9,"name":"Outside Foot Shot"},{"id":10,"name":"Long Shot Taker (CPU AI)"},{"id":12,"name":"Team Player"}],"specialities":[],"position":"CM","skillMoves":4,"weakFoot":4,"foot":"Right","attackWorkRate":"High","defenseWorkRate":"High","totalStats":489,"totalStatsInGame":2366,"color":"gold","rating":85,"ratingAverage":81,"pace":77,"shooting":79,"passing":83,"dribbling":85,"defending":84,"physicality":81,"paceAttributes":{"acceleration":79,"sprintSpeed":76},"shootingAttributes":{"positioning":84,"finishing":77,"shotPower":83,"longShots":80,"volleys":79,"penalties":81},"passingAttributes":{"vision":86,"crossing":80,"freeKickAccuracy":70,"shortPassing":85,"longPassing":85,"curve":84},"dribblingAttributes":{"agility":80,"balance":82,"reactions":89,"ballControl":87,"dribbling":84,"composure":89},"defendingAttributes":{"interceptions":88,"headingAccuracy":68,"standingTackle":86,"slidingTackle":82,"defenseAwareness":85},"physicalityAttributes":{"jumping":66,"stamina":85,"strength":78,"aggression":88},"goalkeeperAttributes":{"diving":null,"handling":null,"kicking":null,"positioning":null,"reflexes":null,"speed":77}},{"id":17104,"resourceId":100906876,"resourceBaseId":243580,"futBinId":50480,"futWizId":19325,"firstName":"Loïs","lastName":"Openda","name":"Loïs Openda","commonName":"Openda","height":174,"weight":78,"birthDate":"2000-02-16","age":23,"league":16,"nation":7,"club":64,"rarity":3,"traits":[{"id":3,"name":"Finesse Shot"},{"id":4,"name":"Solid Player"},{"id":6,"name":"Speed Dribbler (CPU AI)"},{"id":9,"name":"Outside Foot Shot"}],"specialities":[],"position":"ST","skillMoves":3,"weakFoot":3,"foot":"Right","attackWorkRate":"High","defenseWorkRate":"Low","totalStats":469,"totalStatsInGame":2204,"color":"gold","rating":85,"ratingAverage":78,"pace":98,"shooting":85,"passing":78,"dribbling":85,"defending":37,"physicality":86,"paceAttributes":{"acceleration":99,"sprintSpeed":98},"shootingAttributes":{"positioning":88,"finishing":90,"shotPower":85,"longShots":77,"volleys":75,"penalties":86},"passingAttributes":{"vision":82,"crossing":82,"freeKickAccuracy":52,"shortPassing":85,"longPassing":68,"curve":62},"dribblingAttributes":{"agility":91,"balance":91,"reactions":85,"ballControl":83,"dribbling":84,"composure":82},"defendingAttributes":{"interceptions":23,"headingAccuracy":94,"standingTackle":27,"slidingTackle":21,"defenseAwareness":41},"physicalityAttributes":{"jumping":99,"stamina":87,"strength":85,"aggression":82},"goalkeeperAttributes":{"diving":null,"handling":null,"kicking":null,"positioning":null,"reflexes":null,"speed":98}},{"id":17105,"resourceId":67322380,"resourceBaseId":213516,"futBinId":50481,"futWizId":19324,"firstName":"Ricardo Jorge","lastName":"da Luz Horta","name":"Ricardo Horta","commonName":"Ricardo Horta","height":173,"weight":63,"birthDate":"1994-09-15","age":28,"league":308,"nation":38,"club":1896,"rarity":3,"traits":[{"id":2,"name":"Playmaker (CPU AI)"},{"id":3,"name":"Finesse Shot"},{"id":9,"name":"Outside Foot Shot"},{"id":12,"name":"Team Player"},{"id":15,"name":"Early Crosser"},{"id":22,"name":"Leadership"}],"specialities":[],"position":"CAM","skillMoves":3,"weakFoot":3,"foot":"Right","attackWorkRate":"High","defenseWorkRate":"High","totalStats":462,"totalStatsInGame":2237,"color":"gold","rating":85,"ratingAverage":77,"pace":84,"shooting":86,"passing":83,"dribbling":85,"defending":47,"physicality":77,"paceAttributes":{"acceleration":87,"sprintSpeed":82},"shootingAttributes":{"positioning":87,"finishing":85,"shotPower":87,"longShots":88,"volleys":86,"penalties":77},"passingAttributes":{"vision":88,"crossing":81,"freeKickAccuracy":82,"shortPassing":84,"longPassing":78,"curve":84},"dribblingAttributes":{"agility":88,"balance":90,"reactions":87,"ballControl":84,"dribbling":86,"composure":78},"defendingAttributes":{"interceptions":60,"headingAccuracy":60,"standingTackle":48,"slidingTackle":38,"defenseAwareness":35},"physicalityAttributes":{"jumping":69,"stamina":91,"strength":70,"aggression":77},"goalkeeperAttributes":{"diving":null,"handling":null,"kicking":null,"positioning":null,"reflexes":null,"speed":84}},{"id":17125,"resourceId":50566591,"resourceBaseId":234943,"futBinId":50515,"futWizId":19358,"firstName":"Florian","lastName":"Neuhaus","name":"Florian Neuhaus","commonName":"Neuhaus","height":185,"weight":77,"birthDate":"1997-03-16","age":26,"league":19,"nation":21,"club":23,"rarity":151,"traits":[{"id":2,"name":"Playmaker (CPU AI)"},{"id":10,"name":"Long Shot Taker (CPU AI)"}],"specialities":[],"position":"CAM","skillMoves":3,"weakFoot":4,"foot":"Right","attackWorkRate":"Med","defenseWorkRate":"Med","totalStats":470,"totalStatsInGame":2260,"color":"gold","rating":85,"ratingAverage":78,"pace":77,"shooting":80,"passing":85,"dribbling":85,"defending":71,"physicality":72,"paceAttributes":{"acceleration":77,"sprintSpeed":85},"shootingAttributes":{"positioning":82,"finishing":85,"shotPower":87,"longShots":93,"volleys":73,"penalties":62},"passingAttributes":{"vision":87,"crossing":74,"freeKickAccuracy":60,"shortPassing":90,"longPassing":91,"curve":83},"dribblingAttributes":{"agility":84,"balance":83,"reactions":84,"ballControl":85,"dribbling":85,"composure":80},"defendingAttributes":{"interceptions":76,"headingAccuracy":54,"standingTackle":71,"slidingTackle":68,"defenseAwareness":71},"physicalityAttributes":{"jumping":60,"stamina":91,"strength":73,"aggression":66},"goalkeeperAttributes":{"diving":null,"handling":null,"kicking":null,"positioning":null,"reflexes":null,"speed":81}},{"id":17126,"resourceId":50538159,"resourceBaseId":206511,"futBinId":50514,"futWizId":19357,"firstName":"Maximilian","lastName":"Arnold","name":"Maximilian Arnold","commonName":"Arnold","height":184,"weight":74,"birthDate":"1994-05-27","age":28,"league":19,"nation":21,"club":175,"rarity":151,"traits":[{"id":7,"name":"Long Passer (CPU AI)"},{"id":9,"name":"Outside Foot Shot"},{"id":10,"name":"Long Shot Taker (CPU AI)"},{"id":11,"name":"Power Free-Kick"}],"specialities":[],"position":"CDM","skillMoves":3,"weakFoot":3,"foot":"Left","attackWorkRate":"High","defenseWorkRate":"Med","totalStats":489,"totalStatsInGame":2375,"color":"gold","rating":85,"ratingAverage":81,"pace":75,"shooting":85,"passing":84,"dribbling":83,"defending":82,"physicality":80,"paceAttributes":{"acceleration":75,"sprintSpeed":77},"shootingAttributes":{"positioning":80,"finishing":78,"shotPower":91,"longShots":90,"volleys":87,"penalties":59},"passingAttributes":{"vision":85,"crossing":76,"freeKickAccuracy":89,"shortPassing":86,"longPassing":89,"curve":90},"dribblingAttributes":{"agility":78,"balance":78,"reactions":87,"ballControl":88,"dribbling":84,"composure":85},"defendingAttributes":{"interceptions":86,"headingAccuracy":63,"standingTackle":86,"slidingTackle":81,"defenseAwareness":85},"physicalityAttributes":{"jumping":70,"stamina":88,"strength":80,"aggression":84},"goalkeeperAttributes":{"diving":null,"handling":null,"kicking":null,"positioning":null,"reflexes":null,"speed":76}}]}