{"pagination":{"countCurrent":20,"countTotal":17965,"pageCurrent":82,"pageTotal":899,"itemsPerPage":20},"items":[{"id":16413,"resourceId":50541656,"resourceBaseId":210008,"futBinId":48677,"futWizId":17541,"firstName":"Adrien","lastName":"Rabiot","name":"Adrien Rabiot","commonName":"Rabiot","height":192,"weight":80,"birthDate":"1995-04-03","age":27,"league":31,"nation":18,"club":45,"rarity":3,"traits":[],"specialities":[],"position":"CM","skillMoves":3,"weakFoot":3,"foot":"Left","attackWorkRate":"Med","defenseWorkRate":"Med","totalStats":479,"totalStatsInGame":2254,"color":"gold","rating":83,"ratingAverage":79,"pace":78,"shooting":77,"passing":80,"dribbling":83,"defending":79,"physicality":82,"paceAttributes":{"acceleration":73,"sprintSpeed":82},"shootingAttributes":{"positioning":80,"finishing":72,"shotPower":91,"longShots":78,"volleys":72,"penalties":70},"passingAttributes":{"vision":78,"crossing":74,"freeKickAccuracy":63,"shortPassing":87,"longPassing":84,"curve":58},"dribblingAttributes":{"agility":72,"balance":72,"reactions":84,"ballControl":87,"dribbling":84,"composure":84},"defendingAttributes":{"interceptions":83,"headingAccuracy":72,"standingTackle":84,"slidingTackle":76,"defenseAwareness":73},"physicalityAttributes":{"jumping":76,"stamina":90,"strength":83,"aggression":72},"goalkeeperAttributes":{"diving":null,"handling":null,"kicking":null,"positioning":null,"reflexes":null,"speed":77}},{"id":16427,"resourceId":50521972,"resourceBaseId":190324,"futBinId":48669,"futWizId":17542,"firstName":"Christian","lastName":"Kabasele","name":"Christian Kabasele","commonName":"Kabasele","height":188,"weight":84,"birthDate":"1991-02-24","age":32,"league":14,"nation":7,"club":1795,"rarity":87,"traits":[{"id":13,"name":"Dives Into Tackles (CPU AI)"}],"specialities":[],"position":"CB","skillMoves":2,"weakFoot":3,"foot":"Right","attackWorkRate":"Med","defenseWorkRate":"High","totalStats":431,"totalStatsInGame":1993,"color":"gold","rating":83,"ratingAverage":71,"pace":74,"shooting":57,"passing":62,"dribbling":68,"defending":84,"physicality":86,"paceAttributes":{"acceleration":61,"sprintSpeed":85},"shootingAttributes":{"positioning":57,"finishing":56,"shotPower":65,"longShots":50,"volleys":59,"penalties":60},"passingAttributes":{"vision":43,"crossing":56,"freeKickAccuracy":32,"shortPassing":80,"longPassing":70,"curve":41},"dribblingAttributes":{"agility":60,"balance":60,"reactions":83,"ballControl":73,"dribbling":66,"composure":74},"defendingAttributes":{"interceptions":84,"headingAccuracy":82,"standingTackle":82,"slidingTackle":83,"defenseAwareness":86},"physicalityAttributes":{"jumping":94,"stamina":74,"strength":91,"aggression":86},"goalkeeperAttributes":{"diving":null,"handling":null,"kicking":null,"positioning":null,"reflexes":null,"speed":73}},{"id":16430,"resourceId":50590620,"resourceBaseId":258972,"futBinId":48700,"futWizId":17566,"firstName":"Isaak","lastName":"Touré","name":"Isaak Touré","commonName":"Touré","height":204,"weight":75,"birthDate":"2003-03-28","age":19,"league":16,"nation":18,"club":219,"rarity":97,"traits":[],"specialities":[],"position":"ST","skillMoves":3,"weakFoot":4,"foot":"Left","attackWorkRate":"High","defenseWorkRate":"Med","totalStats":465,"totalStatsInGame":2194,"color":"gold","rating":83,"ratingAverage":77,"pace":86,"shooting":83,"passing":78,"dribbling":86,"defending":48,"physicality":84,"paceAttributes":{"acceleration":80,"sprintSpeed":90},"shootingAttributes":{"positioning":99,"finishing":84,"shotPower":97,"longShots":60,"volleys":80,"penalties":99},"passingAttributes":{"vision":81,"crossing":70,"freeKickAccuracy":40,"shortPassing":89,"longPassing":77,"curve":62},"dribblingAttributes":{"agility":76,"balance":80,"reactions":96,"ballControl":95,"dribbling":80,"composure":96},"defendingAttributes":{"interceptions":49,"headingAccuracy":49,"standingTackle":50,"slidingTackle":46,"defenseAwareness":47},"physicalityAttributes":{"jumping":76,"stamina":80,"strength":90,"aggression":76},"goalkeeperAttributes":{"diving":null,"handling":null,"kicking":null,"positioning":null,"reflexes":null,"speed":85}},{"id":16446,"resourceId":50561400,"resourceBaseId":229752,"futBinId":48707,"futWizId":17573,"firstName":"Djibril","lastName":"Sow","name":"Djibril Sow","commonName":"Sow","height":184,"weight":76,"birthDate":"1997-02-06","age":26,"league":19,"nation":47,"club":1824,"rarity":97,"traits":[],"specialities":[],"position":"RB","skillMoves":3,"weakFoot":4,"foot":"Right","attackWorkRate":"Med","defenseWorkRate":"High","totalStats":477,"totalStatsInGame":2245,"color":"gold","rating":83,"ratingAverage":79,"pace":84,"shooting":70,"passing":80,"dribbling":82,"defending":80,"physicality":81,"paceAttributes":{"acceleration":83,"sprintSpeed":85},"shootingAttributes":{"positioning":76,"finishing":70,"shotPower":73,"longShots":71,"volleys":67,"penalties":60},"passingAttributes":{"vision":81,"crossing":73,"freeKickAccuracy":64,"shortPassing":84,"longPassing":86,"curve":71},"dribblingAttributes":{"agility":82,"balance":80,"reactions":81,"ballControl":85,"dribbling":80,"composure":84},"defendingAttributes":{"interceptions":83,"headingAccuracy":66,"standingTackle":82,"slidingTackle":77,"defenseAwareness":80},"physicalityAttributes":{"jumping":74,"stamina":87,"strength":80,"aggression":80},"goalkeeperAttributes":{"diving":null,"handling":null,"kicking":null,"positioning":null,"reflexes":null,"speed":84}},{"id":16459,"resourceId":50504869,"resourceBaseId":173221,"futBinId":48718,"futWizId":17587,"firstName":"Antonio","lastName":"Candreva","name":"Antonio Candreva","commonName":"Candreva","height":180,"weight":70,"birthDate":"1987-02-28","age":36,"league":31,"nation":27,"club":110373,"rarity":3,"traits":[{"id":1,"name":"Technical Dribbler (CPU AI)"},{"id":9,"name":"Outside Foot Shot"},{"id":10,"name":"Long Shot Taker (CPU AI)"},{"id":11,"name":"Power Free-Kick"}],"specialities":[],"position":"CM","skillMoves":4,"weakFoot":4,"foot":"Right","attackWorkRate":"Med","defenseWorkRate":"Med","totalStats":454,"totalStatsInGame":2187,"color":"gold","rating":83,"ratingAverage":75,"pace":75,"shooting":82,"passing":84,"dribbling":84,"defending":64,"physicality":65,"paceAttributes":{"acceleration":78,"sprintSpeed":72},"shootingAttributes":{"positioning":83,"finishing":77,"shotPower":91,"longShots":86,"volleys":82,"penalties":72},"passingAttributes":{"vision":84,"crossing":83,"freeKickAccuracy":77,"shortPassing":86,"longPassing":84,"curve":81},"dribblingAttributes":{"agility":82,"balance":83,"reactions":78,"ballControl":86,"dribbling":84,"composure":76},"defendingAttributes":{"interceptions":70,"headingAccuracy":58,"standingTackle":66,"slidingTackle":56,"defenseAwareness":64},"physicalityAttributes":{"jumping":38,"stamina":84,"strength":57,"aggression":69},"goalkeeperAttributes":{"diving":null,"handling":null,"kicking":null,"positioning":null,"reflexes":null,"speed":75}},{"id":16460,"resourceId":50559598,"resourceBaseId":227950,"futBinId":48719,"futWizId":17588,"firstName":"Yeray","lastName":"Álvarez López","name":"Yeray","commonName":"Yeray","height":182,"weight":79,"birthDate":"1995-01-24","age":28,"league":53,"nation":45,"club":448,"rarity":3,"traits":[{"id":13,"name":"Dives Into Tackles (CPU AI)"}],"specialities":[],"position":"CB","skillMoves":2,"weakFoot":3,"foot":"Right","attackWorkRate":"Med","defenseWorkRate":"Med","totalStats":422,"totalStatsInGame":2032,"color":"gold","rating":83,"ratingAverage":70,"pace":70,"shooting":52,"passing":66,"dribbling":68,"defending":85,"physicality":81,"paceAttributes":{"acceleration":66,"sprintSpeed":73},"shootingAttributes":{"positioning":41,"finishing":45,"shotPower":73,"longShots":46,"volleys":58,"penalties":65},"passingAttributes":{"vision":52,"crossing":51,"freeKickAccuracy":53,"shortPassing":82,"longPassing":73,"curve":61},"dribblingAttributes":{"agility":58,"balance":78,"reactions":85,"ballControl":75,"dribbling":61,"composure":83},"defendingAttributes":{"interceptions":89,"headingAccuracy":77,"standingTackle":84,"slidingTackle":83,"defenseAwareness":86},"physicalityAttributes":{"jumping":94,"stamina":72,"strength":81,"aggression":87},"goalkeeperAttributes":{"diving":null,"handling":null,"kicking":null,"positioning":null,"reflexes":null,"speed":69}},{"id":16461,"resourceId":50548684,"resourceBaseId":217036,"futBinId":48720,"futWizId":17590,"firstName":"Alexandre","lastName":"Moreno Lopera","name":"Álex Moreno","commonName":"Álex Moreno","height":179,"weight":68,"birthDate":"1993-06-08","age":29,"league":53,"nation":45,"club":449,"rarity":3,"traits":[{"id":6,"name":"Speed Dribbler (CPU AI)"},{"id":10,"name":"Long Shot Taker (CPU AI)"},{"id":12,"name":"Team Player"}],"specialities":[],"position":"LB","skillMoves":3,"weakFoot":3,"foot":"Left","attackWorkRate":"High","defenseWorkRate":"Med","totalStats":470,"totalStatsInGame":2201,"color":"gold","rating":83,"ratingAverage":78,"pace":91,"shooting":71,"passing":77,"dribbling":79,"defending":79,"physicality":73,"paceAttributes":{"acceleration":89,"sprintSpeed":93},"shootingAttributes":{"positioning":76,"finishing":76,"shotPower":64,"longShots":68,"volleys":68,"penalties":73},"passingAttributes":{"vision":76,"crossing":80,"freeKickAccuracy":60,"shortPassing":81,"longPassing":72,"curve":73},"dribblingAttributes":{"agility":88,"balance":82,"reactions":77,"ballControl":80,"dribbling":79,"composure":62},"defendingAttributes":{"interceptions":80,"headingAccuracy":66,"standingTackle":82,"slidingTackle":78,"defenseAwareness":81},"physicalityAttributes":{"jumping":66,"stamina":94,"strength":63,"aggression":74},"goalkeeperAttributes":{"diving":null,"handling":null,"kicking":null,"positioning":null,"reflexes":null,"speed":91}},{"id":16476,"resourceId":50545586,"resourceBaseId":213938,"futBinId":48726,"futWizId":17589,"firstName":"Davide","lastName":"Biraschi","name":"Davide Biraschi","commonName":"Biraschi","height":182,"weight":77,"birthDate":"1994-07-02","age":28,"league":68,"nation":27,"club":111117,"rarity":87,"traits":[],"specialities":[],"position":"CB","skillMoves":2,"weakFoot":2,"foot":"Right","attackWorkRate":"Med","defenseWorkRate":"Med","totalStats":443,"totalStatsInGame":2083,"color":"gold","rating":83,"ratingAverage":73,"pace":77,"shooting":46,"passing":72,"dribbling":80,"defending":86,"physicality":82,"paceAttributes":{"acceleration":86,"sprintSpeed":69},"shootingAttributes":{"positioning":60,"finishing":40,"shotPower":70,"longShots":36,"volleys":38,"penalties":41},"passingAttributes":{"vision":65,"crossing":70,"freeKickAccuracy":45,"shortPassing":80,"longPassing":77,"curve":66},"dribblingAttributes":{"agility":79,"balance":79,"reactions":83,"ballControl":80,"dribbling":78,"composure":89},"defendingAttributes":{"interceptions":85,"headingAccuracy":77,"standingTackle":88,"slidingTackle":84,"defenseAwareness":87},"physicalityAttributes":{"jumping":88,"stamina":80,"strength":83,"aggression":80},"goalkeeperAttributes":{"diving":null,"handling":null,"kicking":null,"positioning":null,"reflexes":null,"speed":77}},{"id":16478,"resourceId":50524213,"resourceBaseId":192565,"futBinId":48722,"futWizId":17586,"firstName":"Yunus","lastName":"Mallı","name":"Yunus Malli","commonName":"Malli","height":179,"weight":72,"birthDate":"1992-02-24","age":31,"league":68,"nation":48,"club":111339,"rarity":87,"traits":[{"id":1,"name":"Technical Dribbler (CPU AI)"},{"id":2,"name":"Playmaker (CPU AI)"}],"specialities":[],"position":"CAM","skillMoves":4,"weakFoot":4,"foot":"Right","attackWorkRate":"Med","defenseWorkRate":"Med","totalStats":444,"totalStatsInGame":2183,"color":"gold","rating":83,"ratingAverage":74,"pace":82,"shooting":81,"passing":84,"dribbling":85,"defending":45,"physicality":67,"paceAttributes":{"acceleration":86,"sprintSpeed":78},"shootingAttributes":{"positioning":85,"finishing":80,"shotPower":80,"longShots":80,"volleys":82,"penalties":98},"passingAttributes":{"vision":84,"crossing":82,"freeKickAccuracy":81,"shortPassing":86,"longPassing":81,"curve":86},"dribblingAttributes":{"agility":86,"balance":90,"reactions":80,"ballControl":85,"dribbling":86,"composure":83},"defendingAttributes":{"interceptions":63,"headingAccuracy":54,"standingTackle":40,"slidingTackle":28,"defenseAwareness":42},"physicalityAttributes":{"jumping":79,"stamina":86,"strength":64,"aggression":48},"goalkeeperAttributes":{"diving":null,"handling":null,"kicking":null,"positioning":null,"reflexes":null,"speed":82}},{"id":16797,"resourceId":67361009,"resourceBaseId":252145,"futBinId":50158,"futWizId":19012,"firstName":"Nuno Alexandre","lastName":"Tavares Mendes","name":"Nuno Mendes","commonName":"Nuno Mendes","height":176,"weight":70,"birthDate":"2002-06-19","age":20,"league":16,"nation":38,"club":73,"rarity":3,"traits":[{"id":6,"name":"Speed Dribbler (CPU AI)"},{"id":17,"name":"Long Throw-In"}],"specialities":[],"position":"LB","skillMoves":3,"weakFoot":4,"foot":"Left","attackWorkRate":"High","defenseWorkRate":"Med","totalStats":465,"totalStatsInGame":2191,"color":"gold","rating":83,"ratingAverage":77,"pace":92,"shooting":60,"passing":77,"dribbling":81,"defending":78,"physicality":77,"paceAttributes":{"acceleration":93,"sprintSpeed":92},"shootingAttributes":{"positioning":77,"finishing":47,"shotPower":84,"longShots":66,"volleys":57,"penalties":47},"passingAttributes":{"vision":74,"crossing":82,"freeKickAccuracy":62,"shortPassing":81,"longPassing":74,"curve":70},"dribblingAttributes":{"agility":84,"balance":85,"reactions":81,"ballControl":82,"dribbling":80,"composure":78},"defendingAttributes":{"interceptions":78,"headingAccuracy":72,"standingTackle":82,"slidingTackle":78,"defenseAwareness":77},"physicalityAttributes":{"jumping":74,"stamina":84,"strength":73,"aggression":77},"goalkeeperAttributes":{"diving":null,"handling":null,"kicking":null,"positioning":null,"reflexes":null,"speed":92}},{"id":16798,"resourceId":67353125,"resourceBaseId":244261,"futBinId":50159,"futWizId":19013,"firstName":"Lovro","lastName":"Majer","name":"Lovro Majer","commonName":"Majer","height":179,"weight":75,"birthDate":"1998-01-17","age":25,"league":16,"nation":10,"club":74,"rarity":3,"traits":[{"id":1,"name":"Technical Dribbler (CPU AI)"},{"id":2,"name":"Playmaker (CPU AI)"},{"id":8,"name":"Flair"}],"specialities":[],"position":"CM","skillMoves":4,"weakFoot":3,"foot":"Left","attackWorkRate":"High","defenseWorkRate":"Med","totalStats":455,"totalStatsInGame":2204,"color":"gold","rating":83,"ratingAverage":75,"pace":73,"shooting":77,"passing":84,"dribbling":86,"defending":64,"physicality":71,"paceAttributes":{"acceleration":80,"sprintSpeed":67},"shootingAttributes":{"positioning":81,"finishing":75,"shotPower":80,"longShots":76,"volleys":71,"penalties":82},"passingAttributes":{"vision":84,"crossing":82,"freeKickAccuracy":80,"shortPassing":85,"longPassing":82,"curve":89},"dribblingAttributes":{"agility":87,"balance":71,"reactions":82,"ballControl":88,"dribbling":88,"composure":81},"defendingAttributes":{"interceptions":67,"headingAccuracy":59,"standingTackle":69,"slidingTackle":62,"defenseAwareness":60},"physicalityAttributes":{"jumping":60,"stamina":82,"strength":68,"aggression":66},"goalkeeperAttributes":{"diving":null,"handling":null,"kicking":null,"positioning":null,"reflexes":null,"speed":73}},{"id":17110,"resourceId":50560801,"resourceBaseId":229153,"futBinId":50486,"futWizId":19333,"firstName":"Levi","lastName":"García","name":"Levi García","commonName":"García","height":182,"weight":78,"birthDate":"1997-11-20","age":25,"league":63,"nation":93,"club":278,"rarity":3,"traits":[{"id":1,"name":"Technical Dribbler (CPU AI)"},{"id":8,"name":"Flair"},{"id":14,"name":"Power Header"}],"specialities":[],"position":"RW","skillMoves":4,"weakFoot":3,"foot":"Left","attackWorkRate":"High","defenseWorkRate":"Med","totalStats":460,"totalStatsInGame":2127,"color":"gold","rating":83,"ratingAverage":76,"pace":94,"shooting":76,"passing":80,"dribbling":90,"defending":40,"physicality":80,"paceAttributes":{"acceleration":95,"sprintSpeed":93},"shootingAttributes":{"positioning":70,"finishing":78,"shotPower":78,"longShots":78,"volleys":69,"penalties":50},"passingAttributes":{"vision":83,"crossing":80,"freeKickAccuracy":80,"shortPassing":80,"longPassing":74,"curve":90},"dribblingAttributes":{"agility":87,"balance":88,"reactions":66,"ballControl":93,"dribbling":93,"composure":68},"defendingAttributes":{"interceptions":36,"headingAccuracy":74,"standingTackle":36,"slidingTackle":34,"defenseAwareness":38},"physicalityAttributes":{"jumping":93,"stamina":78,"strength":89,"aggression":56},"goalkeeperAttributes":{"diving":null,"handling":null,"kicking":null,"positioning":null,"reflexes":null,"speed":94}},{"id":17111,"resourceId":67303822,"resourceBaseId":194958,"futBinId":50487,"futWizId":19340,"firstName":"Aaron","lastName":"Mooy","name":"Aaron Mooy","commonName":"Mooy","height":175,"weight":68,"birthDate":"1990-09-15","age":32,"league":50,"nation":195,"club":78,"rarity":3,"traits":[{"id":2,"name":"Playmaker (CPU AI)"},{"id":4,"name":"Solid Player"},{"id":9,"name":"Outside Foot Shot"},{"id":10,"name":"Long Shot Taker (CPU AI)"},{"id":15,"name":"Early Crosser"}],"specialities":[],"position":"CM","skillMoves":3,"weakFoot":3,"foot":"Right","attackWorkRate":"Med","defenseWorkRate":"Med","totalStats":477,"totalStatsInGame":2310,"color":"gold","rating":83,"ratingAverage":79,"pace":73,"shooting":80,"passing":85,"dribbling":81,"defending":76,"physicality":82,"paceAttributes":{"acceleration":79,"sprintSpeed":68},"shootingAttributes":{"positioning":78,"finishing":76,"shotPower":84,"longShots":87,"volleys":73,"penalties":81},"passingAttributes":{"vision":86,"crossing":84,"freeKickAccuracy":78,"shortPassing":87,"longPassing":87,"curve":80},"dribblingAttributes":{"agility":74,"balance":84,"reactions":79,"ballControl":84,"dribbling":80,"composure":88},"defendingAttributes":{"interceptions":77,"headingAccuracy":55,"standingTackle":79,"slidingTackle":76,"defenseAwareness":79},"physicalityAttributes":{"jumping":79,"stamina":85,"strength":81,"aggression":82},"goalkeeperAttributes":{"diving":null,"handling":null,"kicking":null,"positioning":null,"reflexes":null,"speed":73}},{"id":17112,"resourceId":67321096,"resourceBaseId":212232,"futBinId":50488,"futWizId":19331,"firstName":"Jamie","lastName":"Maclaren","name":"Jamie Maclaren","commonName":"Maclaren","height":179,"weight":76,"birthDate":"1993-07-29","age":29,"league":351,"nation":195,"club":112224,"rarity":3,"traits":[{"id":3,"name":"Finesse Shot"},{"id":4,"name":"Solid Player"}],"specialities":[],"position":"ST","skillMoves":3,"weakFoot":5,"foot":"Right","attackWorkRate":"High","defenseWorkRate":"Med","totalStats":461,"totalStatsInGame":2244,"color":"gold","rating":83,"ratingAverage":76,"pace":90,"shooting":84,"passing":76,"dribbling":81,"defending":46,"physicality":84,"paceAttributes":{"acceleration":92,"sprintSpeed":89},"shootingAttributes":{"positioning":92,"finishing":87,"shotPower":83,"longShots":77,"volleys":74,"penalties":83},"passingAttributes":{"vision":78,"crossing":68,"freeKickAccuracy":79,"shortPassing":83,"longPassing":67,"curve":84},"dribblingAttributes":{"agility":94,"balance":90,"reactions":83,"ballControl":78,"dribbling":78,"composure":84},"defendingAttributes":{"interceptions":47,"headingAccuracy":87,"standingTackle":44,"slidingTackle":37,"defenseAwareness":35},"physicalityAttributes":{"jumping":99,"stamina":96,"strength":78,"aggression":78},"goalkeeperAttributes":{"diving":null,"handling":null,"kicking":null,"positioning":null,"reflexes":null,"speed":90}},{"id":17113,"resourceId":67344808,"resourceBaseId":235944,"futBinId":50489,"futWizId":19334,"firstName":"Brais","lastName":"Méndez Portela","name":"Brais Méndez","commonName":"Brais Méndez","height":187,"weight":76,"birthDate":"1997-01-07","age":26,"league":53,"nation":45,"club":457,"rarity":3,"traits":[{"id":1,"name":"Technical Dribbler (CPU AI)"},{"id":2,"name":"Playmaker (CPU AI)"},{"id":3,"name":"Finesse Shot"},{"id":10,"name":"Long Shot Taker (CPU AI)"}],"specialities":[],"position":"CAM","skillMoves":4,"weakFoot":3,"foot":"Left","attackWorkRate":"Med","defenseWorkRate":"Med","totalStats":454,"totalStatsInGame":2147,"color":"gold","rating":83,"ratingAverage":75,"pace":80,"shooting":80,"passing":83,"dribbling":81,"defending":60,"physicality":70,"paceAttributes":{"acceleration":80,"sprintSpeed":80},"shootingAttributes":{"positioning":87,"finishing":82,"shotPower":80,"longShots":79,"volleys":71,"penalties":68},"passingAttributes":{"vision":85,"crossing":82,"freeKickAccuracy":81,"shortPassing":84,"longPassing":81,"curve":80},"dribblingAttributes":{"agility":75,"balance":40,"reactions":84,"ballControl":85,"dribbling":84,"composure":84},"defendingAttributes":{"interceptions":60,"headingAccuracy":57,"standingTackle":71,"slidingTackle":59,"defenseAwareness":53},"physicalityAttributes":{"jumping":70,"stamina":66,"strength":74,"aggression":65},"goalkeeperAttributes":{"diving":null,"handling":null,"kicking":null,"positioning":null,"reflexes":null,"speed":80}},{"id":17114,"resourceId":50517848,"resourceBaseId":186200,"futBinId":50490,"futWizId":19332,"firstName":"Fabio","lastName":"Borini","name":"Fabio Borini","commonName":"Borini","height":180,"weight":73,"birthDate":"1991-03-23","age":32,"league":68,"nation":27,"club":111117,"rarity":3,"traits":[{"id":3,"name":"Finesse Shot"}],"specialities":[],"position":"LW","skillMoves":3,"weakFoot":3,"foot":"Right","attackWorkRate":"High","defenseWorkRate":"Med","totalStats":465,"totalStatsInGame":2231,"color":"gold","rating":83,"ratingAverage":77,"pace":88,"shooting":85,"passing":80,"dribbling":85,"defending":50,"physicality":77,"paceAttributes":{"acceleration":92,"sprintSpeed":84},"shootingAttributes":{"positioning":91,"finishing":84,"shotPower":87,"longShots":83,"volleys":86,"penalties":90},"passingAttributes":{"vision":80,"crossing":82,"freeKickAccuracy":68,"shortPassing":84,"longPassing":69,"curve":80},"dribblingAttributes":{"agility":87,"balance":75,"reactions":86,"ballControl":85,"dribbling":86,"composure":85},"defendingAttributes":{"interceptions":33,"headingAccuracy":82,"standingTackle":33,"slidingTackle":29,"defenseAwareness":76},"physicalityAttributes":{"jumping":80,"stamina":78,"strength":74,"aggression":82},"goalkeeperAttributes":{"diving":null,"handling":null,"kicking":null,"positioning":null,"reflexes":null,"speed":88}},{"id":17115,"resourceId":67334011,"resourceBaseId":225147,"futBinId":50491,"futWizId":19330,"firstName":"Connor","lastName":"Roberts","name":"Connor Roberts","commonName":"Roberts","height":175,"weight":76,"birthDate":"1995-09-23","age":27,"league":14,"nation":50,"club":1796,"rarity":3,"traits":[{"id":17,"name":"Long Throw-In"}],"specialities":[],"position":"RB","skillMoves":3,"weakFoot":4,"foot":"Right","attackWorkRate":"High","defenseWorkRate":"Med","totalStats":463,"totalStatsInGame":2131,"color":"gold","rating":83,"ratingAverage":77,"pace":86,"shooting":60,"passing":77,"dribbling":78,"defending":80,"physicality":82,"paceAttributes":{"acceleration":87,"sprintSpeed":85},"shootingAttributes":{"positioning":67,"finishing":56,"shotPower":66,"longShots":61,"volleys":52,"penalties":45},"passingAttributes":{"vision":72,"crossing":86,"freeKickAccuracy":55,"shortPassing":84,"longPassing":68,"curve":63},"dribblingAttributes":{"agility":80,"balance":79,"reactions":77,"ballControl":80,"dribbling":78,"composure":70},"defendingAttributes":{"interceptions":81,"headingAccuracy":66,"standingTackle":85,"slidingTackle":80,"defenseAwareness":80},"physicalityAttributes":{"jumping":77,"stamina":99,"strength":75,"aggression":77},"goalkeeperAttributes":{"diving":null,"handling":null,"kicking":null,"positioning":null,"reflexes":null,"speed":86}},{"id":16374,"resourceId":50528873,"resourceBaseId":197225,"futBinId":48634,"futWizId":17501,"firstName":"Nicolas","lastName":"Lodeiro","name":"Nicolás Lodeiro","commonName":"Lodeiro","height":170,"weight":69,"birthDate":"1989-03-21","age":34,"league":39,"nation":60,"club":111144,"rarity":87,"traits":[{"id":1,"name":"Technical Dribbler (CPU AI)"},{"id":2,"name":"Playmaker (CPU AI)"},{"id":8,"name":"Flair"},{"id":9,"name":"Outside Foot Shot"},{"id":10,"name":"Long Shot Taker (CPU AI)"},{"id":22,"name":"Leadership"}],"specialities":[],"position":"CAM","skillMoves":4,"weakFoot":3,"foot":"Left","attackWorkRate":"High","defenseWorkRate":"Med","totalStats":455,"totalStatsInGame":2207,"color":"gold","rating":83,"ratingAverage":75,"pace":76,"shooting":80,"passing":86,"dribbling":87,"defending":53,"physicality":73,"paceAttributes":{"acceleration":80,"sprintSpeed":72},"shootingAttributes":{"positioning":83,"finishing":78,"shotPower":78,"longShots":83,"volleys":77,"penalties":87},"passingAttributes":{"vision":87,"crossing":85,"freeKickAccuracy":84,"shortPassing":88,"longPassing":82,"curve":87},"dribblingAttributes":{"agility":87,"balance":86,"reactions":85,"ballControl":87,"dribbling":87,"composure":88},"defendingAttributes":{"interceptions":53,"headingAccuracy":46,"standingTackle":56,"slidingTackle":43,"defenseAwareness":54},"physicalityAttributes":{"jumping":57,"stamina":84,"strength":70,"aggression":73},"goalkeeperAttributes":{"diving":null,"handling":null,"kicking":null,"positioning":null,"reflexes":null,"speed":76}},{"id":16375,"resourceId":50533979,"resourceBaseId":202331,"futBinId":48633,"futWizId":17500,"firstName":"Facundo","lastName":"Quignon","name":"Facundo Quignon","commonName":"Quignon","height":178,"weight":73,"birthDate":"1993-05-02","age":29,"league":39,"nation":52,"club":695,"rarity":87,"traits":[{"id":7,"name":"Long Passer (CPU AI)"}],"specialities":[],"position":"CDM","skillMoves":3,"weakFoot":4,"foot":"Left","attackWorkRate":"Med","defenseWorkRate":"High","totalStats":478,"totalStatsInGame":2290,"color":"gold","rating":83,"ratingAverage":79,"pace":76,"shooting":70,"passing":78,"dribbling":84,"defending":83,"physicality":87,"paceAttributes":{"acceleration":82,"sprintSpeed":71},"shootingAttributes":{"positioning":70,"finishing":61,"shotPower":91,"longShots":70,"volleys":69,"penalties":74},"passingAttributes":{"vision":77,"crossing":65,"freeKickAccuracy":59,"shortPassing":89,"longPassing":83,"curve":70},"dribblingAttributes":{"agility":81,"balance":76,"reactions":75,"ballControl":89,"dribbling":83,"composure":84},"defendingAttributes":{"interceptions":78,"headingAccuracy":85,"standingTackle":84,"slidingTackle":81,"defenseAwareness":84},"physicalityAttributes":{"jumping":94,"stamina":93,"strength":81,"aggression":91},"goalkeeperAttributes":{"diving":null,"handling":null,"kicking":null,"positioning":null,"reflexes":null,"speed":76}},{"id":16379,"resourceId":50569590,"resourceBaseId":237942,"futBinId":48648,"futWizId":17515,"firstName":"Pervis","lastName":"Estupiñán","name":"Pervis Estupiñán","commonName":"Estupiñán","height":175,"weight":78,"birthDate":"1998-01-21","age":25,"league":13,"nation":57,"club":1808,"rarity":22,"traits":[{"id":6,"name":"Speed Dribbler (CPU AI)"}],"specialities":[],"position":"LB","skillMoves":3,"weakFoot":4,"foot":"Left","attackWorkRate":"High","defenseWorkRate":"Med","totalStats":450,"totalStatsInGame":2069,"color":"gold","rating":83,"ratingAverage":75,"pace":87,"shooting":51,"passing":77,"dribbling":70,"defending":84,"physicality":81,"paceAttributes":{"acceleration":86,"sprintSpeed":88},"shootingAttributes":{"positioning":58,"finishing":53,"shotPower":45,"longShots":47,"volleys":42,"penalties":77},"passingAttributes":{"vision":62,"crossing":88,"freeKickAccuracy":41,"shortPassing":88,"longPassing":69,"curve":66},"dribblingAttributes":{"agility":72,"balance":71,"reactions":72,"ballControl":69,"dribbling":71,"composure":63},"defendingAttributes":{"interceptions":84,"headingAccuracy":84,"standingTackle":90,"slidingTackle":88,"defenseAwareness":77},"physicalityAttributes":{"jumping":75,"stamina":83,"strength":83,"aggression":77},"goalkeeperAttributes":{"diving":null,"handling":null,"kicking":null,"positioning":null,"reflexes":null,"speed":87}}]}