{"pagination":{"countCurrent":20,"countTotal":17965,"pageCurrent":279,"pageTotal":899,"itemsPerPage":20},"items":[{"id":8459,"resourceId":200779,"resourceBaseId":200779,"futBinId":29125,"futWizId":9565,"firstName":"Jonson","lastName":"Clarke-Harris","name":"Jonson Clarke-Harris","commonName":"Clarke-Harris","height":183,"weight":0,"birthDate":"1994-07-21","age":28,"league":60,"nation":82,"club":1938,"rarity":0,"traits":[],"specialities":[],"position":"ST","skillMoves":3,"weakFoot":4,"foot":"Left","attackWorkRate":"Med","defenseWorkRate":"Low","totalStats":377,"totalStatsInGame":1778,"color":"silver","rating":71,"ratingAverage":62,"pace":77,"shooting":72,"passing":55,"dribbling":68,"defending":27,"physicality":78,"paceAttributes":{"acceleration":76,"sprintSpeed":78},"shootingAttributes":{"positioning":70,"finishing":72,"shotPower":79,"longShots":69,"volleys":66,"penalties":73},"passingAttributes":{"vision":58,"crossing":45,"freeKickAccuracy":64,"shortPassing":61,"longPassing":43,"curve":58},"dribblingAttributes":{"agility":72,"balance":68,"reactions":68,"ballControl":68,"dribbling":66,"composure":72},"defendingAttributes":{"interceptions":30,"headingAccuracy":67,"standingTackle":17,"slidingTackle":13,"defenseAwareness":27},"physicalityAttributes":{"jumping":74,"stamina":68,"strength":86,"aggression":70},"goalkeeperAttributes":{"diving":null,"handling":null,"kicking":null,"positioning":null,"reflexes":null,"speed":77}},{"id":8204,"resourceId":243606,"resourceBaseId":243606,"futBinId":34449,"futWizId":9621,"firstName":"Keane","lastName":"Lewis-Potter","name":"Keane Lewis-Potter","commonName":"Lewis-Potter","height":170,"weight":0,"birthDate":"2001-02-22","age":22,"league":13,"nation":14,"club":1925,"rarity":0,"traits":[],"specialities":[],"position":"LW","skillMoves":3,"weakFoot":4,"foot":"Right","attackWorkRate":"High","defenseWorkRate":"Med","totalStats":378,"totalStatsInGame":1809,"color":"silver","rating":71,"ratingAverage":63,"pace":81,"shooting":67,"passing":64,"dribbling":72,"defending":36,"physicality":58,"paceAttributes":{"acceleration":84,"sprintSpeed":79},"shootingAttributes":{"positioning":68,"finishing":68,"shotPower":68,"longShots":67,"volleys":57,"penalties":58},"passingAttributes":{"vision":66,"crossing":68,"freeKickAccuracy":61,"shortPassing":64,"longPassing":54,"curve":64},"dribblingAttributes":{"agility":84,"balance":82,"reactions":67,"ballControl":70,"dribbling":72,"composure":64},"defendingAttributes":{"interceptions":34,"headingAccuracy":64,"standingTackle":30,"slidingTackle":32,"defenseAwareness":36},"physicalityAttributes":{"jumping":75,"stamina":77,"strength":54,"aggression":42},"goalkeeperAttributes":{"diving":null,"handling":null,"kicking":null,"positioning":null,"reflexes":null,"speed":81}},{"id":8213,"resourceId":250810,"resourceBaseId":250810,"futBinId":35469,"futWizId":9251,"firstName":"Marvin","lastName":"Ekpiteta","name":"Marvin Ekpiteta","commonName":"Ekpiteta","height":193,"weight":0,"birthDate":"1995-08-26","age":27,"league":14,"nation":14,"club":1926,"rarity":0,"traits":[],"specialities":[],"position":"CB","skillMoves":2,"weakFoot":1,"foot":"Right","attackWorkRate":"Med","defenseWorkRate":"Med","totalStats":345,"totalStatsInGame":1560,"color":"silver","rating":71,"ratingAverage":57,"pace":69,"shooting":29,"passing":48,"dribbling":52,"defending":71,"physicality":76,"paceAttributes":{"acceleration":68,"sprintSpeed":70},"shootingAttributes":{"positioning":36,"finishing":25,"shotPower":40,"longShots":23,"volleys":28,"penalties":36},"passingAttributes":{"vision":44,"crossing":39,"freeKickAccuracy":31,"shortPassing":59,"longPassing":52,"curve":35},"dribblingAttributes":{"agility":44,"balance":49,"reactions":67,"ballControl":56,"dribbling":49,"composure":68},"defendingAttributes":{"interceptions":69,"headingAccuracy":69,"standingTackle":72,"slidingTackle":70,"defenseAwareness":73},"physicalityAttributes":{"jumping":67,"stamina":68,"strength":85,"aggression":68},"goalkeeperAttributes":{"diving":null,"handling":null,"kicking":null,"positioning":null,"reflexes":null,"speed":69}},{"id":7960,"resourceId":240638,"resourceBaseId":240638,"futBinId":33829,"futWizId":9363,"firstName":"Tijjani","lastName":"Reijnders","name":"Tijjani Reijnders","commonName":"Reijnders","height":185,"weight":0,"birthDate":"1998-07-29","age":24,"league":10,"nation":34,"club":1906,"rarity":1,"traits":[],"specialities":[],"position":"CM","skillMoves":3,"weakFoot":4,"foot":"Right","attackWorkRate":"Med","defenseWorkRate":"Med","totalStats":418,"totalStatsInGame":1988,"color":"silver","rating":71,"ratingAverage":69,"pace":78,"shooting":68,"passing":70,"dribbling":74,"defending":61,"physicality":67,"paceAttributes":{"acceleration":80,"sprintSpeed":76},"shootingAttributes":{"positioning":62,"finishing":64,"shotPower":76,"longShots":76,"volleys":62,"penalties":57},"passingAttributes":{"vision":72,"crossing":69,"freeKickAccuracy":59,"shortPassing":72,"longPassing":70,"curve":66},"dribblingAttributes":{"agility":84,"balance":74,"reactions":73,"ballControl":73,"dribbling":72,"composure":75},"defendingAttributes":{"interceptions":64,"headingAccuracy":55,"standingTackle":61,"slidingTackle":58,"defenseAwareness":63},"physicalityAttributes":{"jumping":73,"stamina":75,"strength":64,"aggression":63},"goalkeeperAttributes":{"diving":null,"handling":null,"kicking":null,"positioning":null,"reflexes":null,"speed":78}},{"id":8486,"resourceId":260478,"resourceBaseId":260478,"futBinId":37239,"futWizId":9433,"firstName":"Sorba","lastName":"Thomas","name":"Sorba Thomas","commonName":"Thomas","height":185,"weight":0,"birthDate":"1999-01-25","age":24,"league":14,"nation":50,"club":1939,"rarity":1,"traits":[],"specialities":[],"position":"RW","skillMoves":3,"weakFoot":3,"foot":"Right","attackWorkRate":"High","defenseWorkRate":"High","totalStats":411,"totalStatsInGame":1907,"color":"silver","rating":71,"ratingAverage":68,"pace":87,"shooting":65,"passing":69,"dribbling":71,"defending":50,"physicality":69,"paceAttributes":{"acceleration":88,"sprintSpeed":86},"shootingAttributes":{"positioning":65,"finishing":63,"shotPower":74,"longShots":64,"volleys":55,"penalties":53},"passingAttributes":{"vision":67,"crossing":77,"freeKickAccuracy":73,"shortPassing":67,"longPassing":65,"curve":76},"dribblingAttributes":{"agility":73,"balance":76,"reactions":64,"ballControl":69,"dribbling":72,"composure":67},"defendingAttributes":{"interceptions":45,"headingAccuracy":43,"standingTackle":54,"slidingTackle":49,"defenseAwareness":53},"physicalityAttributes":{"jumping":48,"stamina":83,"strength":61,"aggression":77},"goalkeeperAttributes":{"diving":null,"handling":null,"kicking":null,"positioning":null,"reflexes":null,"speed":87}},{"id":8487,"resourceId":50550941,"resourceBaseId":219293,"futBinId":38018,"futWizId":9222,"firstName":"Michał","lastName":"Helik","name":"Michał Helik","commonName":"Helik","height":191,"weight":80,"birthDate":"1995-09-09","age":27,"league":14,"nation":37,"club":1939,"rarity":0,"traits":[{"id":7,"name":"Long Passer (CPU AI)"},{"id":13,"name":"Dives Into Tackles (CPU AI)"},{"id":14,"name":"Power Header"}],"specialities":[],"position":"CB","skillMoves":2,"weakFoot":3,"foot":"Right","attackWorkRate":"Med","defenseWorkRate":"Med","totalStats":357,"totalStatsInGame":1676,"color":"silver","rating":71,"ratingAverage":59,"pace":62,"shooting":49,"passing":47,"dribbling":53,"defending":70,"physicality":76,"paceAttributes":{"acceleration":59,"sprintSpeed":64},"shootingAttributes":{"positioning":61,"finishing":52,"shotPower":52,"longShots":41,"volleys":49,"penalties":37},"passingAttributes":{"vision":34,"crossing":41,"freeKickAccuracy":40,"shortPassing":61,"longPassing":51,"curve":29},"dribblingAttributes":{"agility":53,"balance":59,"reactions":70,"ballControl":59,"dribbling":46,"composure":55},"defendingAttributes":{"interceptions":74,"headingAccuracy":73,"standingTackle":69,"slidingTackle":65,"defenseAwareness":69},"physicalityAttributes":{"jumping":91,"stamina":71,"strength":79,"aggression":72},"goalkeeperAttributes":{"diving":null,"handling":null,"kicking":null,"positioning":null,"reflexes":null,"speed":61}},{"id":7981,"resourceId":229435,"resourceBaseId":229435,"futBinId":32075,"futWizId":9260,"firstName":"Michel","lastName":"Vlap","name":"Michel Vlap","commonName":"Vlap","height":190,"weight":0,"birthDate":"1997-06-02","age":25,"league":10,"nation":34,"club":1908,"rarity":1,"traits":[],"specialities":[],"position":"CAM","skillMoves":3,"weakFoot":4,"foot":"Right","attackWorkRate":"High","defenseWorkRate":"Med","totalStats":382,"totalStatsInGame":1866,"color":"silver","rating":71,"ratingAverage":63,"pace":58,"shooting":73,"passing":69,"dribbling":70,"defending":47,"physicality":65,"paceAttributes":{"acceleration":65,"sprintSpeed":52},"shootingAttributes":{"positioning":77,"finishing":73,"shotPower":72,"longShots":73,"volleys":66,"penalties":74},"passingAttributes":{"vision":72,"crossing":64,"freeKickAccuracy":74,"shortPassing":71,"longPassing":65,"curve":72},"dribblingAttributes":{"agility":68,"balance":51,"reactions":71,"ballControl":73,"dribbling":71,"composure":74},"defendingAttributes":{"interceptions":40,"headingAccuracy":74,"standingTackle":36,"slidingTackle":34,"defenseAwareness":58},"physicalityAttributes":{"jumping":59,"stamina":73,"strength":71,"aggression":43},"goalkeeperAttributes":{"diving":null,"handling":null,"kicking":null,"positioning":null,"reflexes":null,"speed":58}},{"id":7982,"resourceId":209818,"resourceBaseId":209818,"futBinId":29908,"futWizId":9316,"firstName":"Joshua","lastName":"Brenet","name":"Joshua Brenet","commonName":"Brenet","height":181,"weight":0,"birthDate":"1994-03-20","age":29,"league":10,"nation":34,"club":1908,"rarity":0,"traits":[],"specialities":[],"position":"RB","skillMoves":3,"weakFoot":3,"foot":"Right","attackWorkRate":"High","defenseWorkRate":"Med","totalStats":381,"totalStatsInGame":1749,"color":"silver","rating":71,"ratingAverage":63,"pace":79,"shooting":36,"passing":61,"dribbling":70,"defending":68,"physicality":67,"paceAttributes":{"acceleration":82,"sprintSpeed":77},"shootingAttributes":{"positioning":58,"finishing":36,"shotPower":33,"longShots":31,"volleys":35,"penalties":56},"passingAttributes":{"vision":58,"crossing":65,"freeKickAccuracy":31,"shortPassing":67,"longPassing":62,"curve":50},"dribblingAttributes":{"agility":69,"balance":69,"reactions":66,"ballControl":69,"dribbling":72,"composure":63},"defendingAttributes":{"interceptions":67,"headingAccuracy":66,"standingTackle":70,"slidingTackle":69,"defenseAwareness":68},"physicalityAttributes":{"jumping":59,"stamina":63,"strength":68,"aggression":70},"goalkeeperAttributes":{"diving":null,"handling":null,"kicking":null,"positioning":null,"reflexes":null,"speed":79}},{"id":8005,"resourceId":235297,"resourceBaseId":235297,"futBinId":32904,"futWizId":9400,"firstName":"Matúš","lastName":"Bero","name":"Matúš Bero","commonName":"Bero","height":181,"weight":0,"birthDate":"1995-09-06","age":27,"league":10,"nation":43,"club":1909,"rarity":1,"traits":[],"specialities":[],"position":"CM","skillMoves":3,"weakFoot":3,"foot":"Right","attackWorkRate":"High","defenseWorkRate":"High","totalStats":432,"totalStatsInGame":2052,"color":"silver","rating":71,"ratingAverage":72,"pace":72,"shooting":71,"passing":69,"dribbling":71,"defending":67,"physicality":82,"paceAttributes":{"acceleration":69,"sprintSpeed":75},"shootingAttributes":{"positioning":75,"finishing":70,"shotPower":75,"longShots":69,"volleys":69,"penalties":67},"passingAttributes":{"vision":68,"crossing":66,"freeKickAccuracy":64,"shortPassing":71,"longPassing":69,"curve":69},"dribblingAttributes":{"agility":69,"balance":73,"reactions":73,"ballControl":71,"dribbling":72,"composure":68},"defendingAttributes":{"interceptions":66,"headingAccuracy":62,"standingTackle":65,"slidingTackle":61,"defenseAwareness":73},"physicalityAttributes":{"jumping":73,"stamina":91,"strength":80,"aggression":79},"goalkeeperAttributes":{"diving":null,"handling":null,"kicking":null,"positioning":null,"reflexes":null,"speed":72}},{"id":8006,"resourceId":228591,"resourceBaseId":228591,"futBinId":31955,"futWizId":9751,"firstName":"Carlens","lastName":"Arcus","name":"Carlens Arcus","commonName":"Arcus","height":176,"weight":0,"birthDate":"1996-06-28","age":26,"league":10,"nation":80,"club":1909,"rarity":0,"traits":[],"specialities":[],"position":"RWB","skillMoves":2,"weakFoot":2,"foot":"Right","attackWorkRate":"Med","defenseWorkRate":"Med","totalStats":382,"totalStatsInGame":1796,"color":"silver","rating":71,"ratingAverage":63,"pace":71,"shooting":42,"passing":64,"dribbling":65,"defending":67,"physicality":73,"paceAttributes":{"acceleration":70,"sprintSpeed":71},"shootingAttributes":{"positioning":65,"finishing":38,"shotPower":53,"longShots":37,"volleys":39,"penalties":42},"passingAttributes":{"vision":65,"crossing":67,"freeKickAccuracy":39,"shortPassing":69,"longPassing":63,"curve":47},"dribblingAttributes":{"agility":66,"balance":77,"reactions":65,"ballControl":71,"dribbling":60,"composure":65},"defendingAttributes":{"interceptions":65,"headingAccuracy":62,"standingTackle":72,"slidingTackle":70,"defenseAwareness":65},"physicalityAttributes":{"jumping":78,"stamina":76,"strength":73,"aggression":66},"goalkeeperAttributes":{"diving":null,"handling":null,"kicking":null,"positioning":null,"reflexes":null,"speed":70}},{"id":8053,"resourceId":213000,"resourceBaseId":213000,"futBinId":30259,"futWizId":9275,"firstName":"Sven","lastName":"van Beek","name":"Sven van Beek","commonName":"van Beek","height":190,"weight":0,"birthDate":"1994-07-28","age":28,"league":10,"nation":34,"club":1913,"rarity":0,"traits":[],"specialities":[],"position":"CB","skillMoves":2,"weakFoot":2,"foot":"Right","attackWorkRate":"Low","defenseWorkRate":"Med","totalStats":349,"totalStatsInGame":1608,"color":"silver","rating":71,"ratingAverage":58,"pace":60,"shooting":39,"passing":55,"dribbling":51,"defending":72,"physicality":72,"paceAttributes":{"acceleration":52,"sprintSpeed":66},"shootingAttributes":{"positioning":20,"finishing":34,"shotPower":64,"longShots":30,"volleys":29,"penalties":54},"passingAttributes":{"vision":43,"crossing":42,"freeKickAccuracy":26,"shortPassing":70,"longPassing":71,"curve":30},"dribblingAttributes":{"agility":47,"balance":53,"reactions":67,"ballControl":57,"dribbling":45,"composure":65},"defendingAttributes":{"interceptions":69,"headingAccuracy":73,"standingTackle":73,"slidingTackle":71,"defenseAwareness":73},"physicalityAttributes":{"jumping":74,"stamina":68,"strength":76,"aggression":66},"goalkeeperAttributes":{"diving":null,"handling":null,"kicking":null,"positioning":null,"reflexes":null,"speed":59}},{"id":8074,"resourceId":255233,"resourceBaseId":255233,"futBinId":36264,"futWizId":9279,"firstName":"Tomáš","lastName":"Suslov","name":"Tomáš Suslov","commonName":"Suslov","height":173,"weight":0,"birthDate":"2002-06-07","age":20,"league":10,"nation":43,"club":1915,"rarity":0,"traits":[],"specialities":[],"position":"CAM","skillMoves":3,"weakFoot":3,"foot":"Left","attackWorkRate":"High","defenseWorkRate":"High","totalStats":396,"totalStatsInGame":1848,"color":"silver","rating":71,"ratingAverage":66,"pace":74,"shooting":65,"passing":70,"dribbling":74,"defending":48,"physicality":65,"paceAttributes":{"acceleration":75,"sprintSpeed":74},"shootingAttributes":{"positioning":64,"finishing":63,"shotPower":70,"longShots":69,"volleys":56,"penalties":60},"passingAttributes":{"vision":72,"crossing":61,"freeKickAccuracy":72,"shortPassing":74,"longPassing":72,"curve":70},"dribblingAttributes":{"agility":72,"balance":86,"reactions":59,"ballControl":74,"dribbling":76,"composure":61},"defendingAttributes":{"interceptions":42,"headingAccuracy":40,"standingTackle":52,"slidingTackle":46,"defenseAwareness":50},"physicalityAttributes":{"jumping":33,"stamina":80,"strength":62,"aggression":63},"goalkeeperAttributes":{"diving":null,"handling":null,"kicking":null,"positioning":null,"reflexes":null,"speed":74}},{"id":8101,"resourceId":228684,"resourceBaseId":228684,"futBinId":31973,"futWizId":9551,"firstName":"Ryan","lastName":"Nyambe","name":"Ryan Nyambe","commonName":"Nyambe","height":178,"weight":0,"birthDate":"1997-12-04","age":25,"league":14,"nation":131,"club":1917,"rarity":1,"traits":[],"specialities":[],"position":"RWB","skillMoves":3,"weakFoot":3,"foot":"Right","attackWorkRate":"Med","defenseWorkRate":"High","totalStats":385,"totalStatsInGame":1727,"color":"silver","rating":71,"ratingAverage":64,"pace":81,"shooting":33,"passing":58,"dribbling":69,"defending":68,"physicality":76,"paceAttributes":{"acceleration":81,"sprintSpeed":81},"shootingAttributes":{"positioning":52,"finishing":32,"shotPower":34,"longShots":30,"volleys":30,"penalties":36},"passingAttributes":{"vision":43,"crossing":67,"freeKickAccuracy":38,"shortPassing":66,"longPassing":59,"curve":46},"dribblingAttributes":{"agility":73,"balance":70,"reactions":64,"ballControl":66,"dribbling":71,"composure":58},"defendingAttributes":{"interceptions":65,"headingAccuracy":63,"standingTackle":70,"slidingTackle":68,"defenseAwareness":70},"physicalityAttributes":{"jumping":76,"stamina":77,"strength":83,"aggression":58},"goalkeeperAttributes":{"diving":null,"handling":null,"kicking":null,"positioning":null,"reflexes":null,"speed":81}},{"id":7870,"resourceId":178571,"resourceBaseId":178571,"futBinId":28103,"futWizId":9455,"firstName":"Rafael","lastName":"Wihby Bracali","name":"Rafael Wihby Bracali","commonName":"Bracali","height":185,"weight":0,"birthDate":"1981-05-05","age":41,"league":308,"nation":54,"club":1898,"rarity":1,"traits":[],"specialities":[],"position":"GK","skillMoves":1,"weakFoot":2,"foot":"Right","attackWorkRate":"Med","defenseWorkRate":"Med","totalStats":381,"totalStatsInGame":931,"color":"silver","rating":71,"ratingAverage":63,"pace":40,"shooting":21,"passing":25,"dribbling":47,"defending":15,"physicality":51,"paceAttributes":{"acceleration":37,"sprintSpeed":43},"shootingAttributes":{"positioning":12,"finishing":14,"shotPower":45,"longShots":17,"volleys":19,"penalties":23},"passingAttributes":{"vision":45,"crossing":10,"freeKickAccuracy":11,"shortPassing":38,"longPassing":36,"curve":15},"dribblingAttributes":{"agility":59,"balance":68,"reactions":67,"ballControl":29,"dribbling":14,"composure":47},"defendingAttributes":{"interceptions":21,"headingAccuracy":10,"standingTackle":14,"slidingTackle":17,"defenseAwareness":16},"physicalityAttributes":{"jumping":75,"stamina":31,"strength":69,"aggression":29},"goalkeeperAttributes":{"diving":71,"handling":71,"kicking":60,"positioning":71,"reflexes":69,"speed":39}},{"id":8135,"resourceId":205054,"resourceBaseId":205054,"futBinId":29524,"futWizId":9483,"firstName":"Kal","lastName":"Naismith","name":"Kal Naismith","commonName":"Naismith","height":185,"weight":0,"birthDate":"1992-02-18","age":31,"league":14,"nation":42,"club":1919,"rarity":1,"traits":[],"specialities":[],"position":"CB","skillMoves":3,"weakFoot":3,"foot":"Left","attackWorkRate":"High","defenseWorkRate":"Med","totalStats":411,"totalStatsInGame":1966,"color":"silver","rating":71,"ratingAverage":68,"pace":67,"shooting":65,"passing":65,"dribbling":67,"defending":70,"physicality":77,"paceAttributes":{"acceleration":69,"sprintSpeed":66},"shootingAttributes":{"positioning":52,"finishing":63,"shotPower":73,"longShots":71,"volleys":45,"penalties":59},"passingAttributes":{"vision":64,"crossing":67,"freeKickAccuracy":74,"shortPassing":64,"longPassing":61,"curve":68},"dribblingAttributes":{"agility":74,"balance":74,"reactions":69,"ballControl":64,"dribbling":67,"composure":61},"defendingAttributes":{"interceptions":70,"headingAccuracy":70,"standingTackle":71,"slidingTackle":69,"defenseAwareness":70},"physicalityAttributes":{"jumping":81,"stamina":79,"strength":78,"aggression":73},"goalkeeperAttributes":{"diving":null,"handling":null,"kicking":null,"positioning":null,"reflexes":null,"speed":67}},{"id":8136,"resourceId":199383,"resourceBaseId":199383,"futBinId":44402,"futWizId":9389,"firstName":"Timm","lastName":"Klose","name":"Timm Klose","commonName":"Klose","height":194,"weight":0,"birthDate":"1988-05-09","age":34,"league":14,"nation":47,"club":1919,"rarity":1,"traits":[],"specialities":[],"position":"CB","skillMoves":2,"weakFoot":3,"foot":"Right","attackWorkRate":"Low","defenseWorkRate":"Med","totalStats":303,"totalStatsInGame":1465,"color":"silver","rating":71,"ratingAverage":50,"pace":32,"shooting":38,"passing":54,"dribbling":38,"defending":74,"physicality":67,"paceAttributes":{"acceleration":31,"sprintSpeed":32},"shootingAttributes":{"positioning":40,"finishing":29,"shotPower":64,"longShots":35,"volleys":32,"penalties":30},"passingAttributes":{"vision":54,"crossing":34,"freeKickAccuracy":26,"shortPassing":66,"longPassing":69,"curve":38},"dribblingAttributes":{"agility":28,"balance":29,"reactions":68,"ballControl":45,"dribbling":28,"composure":75},"defendingAttributes":{"interceptions":73,"headingAccuracy":78,"standingTackle":74,"slidingTackle":71,"defenseAwareness":73},"physicalityAttributes":{"jumping":56,"stamina":34,"strength":83,"aggression":70},"goalkeeperAttributes":{"diving":null,"handling":null,"kicking":null,"positioning":null,"reflexes":null,"speed":31}},{"id":7899,"resourceId":204370,"resourceBaseId":204370,"futBinId":29464,"futWizId":9763,"firstName":"Sander","lastName":"van de Streek","name":"Sander van de Streek","commonName":"van de Streek","height":180,"weight":0,"birthDate":"1993-03-24","age":30,"league":10,"nation":34,"club":1903,"rarity":1,"traits":[],"specialities":[],"position":"CAM","skillMoves":3,"weakFoot":3,"foot":"Right","attackWorkRate":"High","defenseWorkRate":"Med","totalStats":401,"totalStatsInGame":1958,"color":"silver","rating":71,"ratingAverage":66,"pace":64,"shooting":72,"passing":68,"dribbling":71,"defending":58,"physicality":68,"paceAttributes":{"acceleration":60,"sprintSpeed":67},"shootingAttributes":{"positioning":74,"finishing":72,"shotPower":75,"longShots":74,"volleys":67,"penalties":64},"passingAttributes":{"vision":70,"crossing":59,"freeKickAccuracy":56,"shortPassing":72,"longPassing":70,"curve":69},"dribblingAttributes":{"agility":68,"balance":69,"reactions":74,"ballControl":73,"dribbling":70,"composure":73},"defendingAttributes":{"interceptions":61,"headingAccuracy":78,"standingTackle":61,"slidingTackle":48,"defenseAwareness":50},"physicalityAttributes":{"jumping":87,"stamina":75,"strength":68,"aggression":54},"goalkeeperAttributes":{"diving":null,"handling":null,"kicking":null,"positioning":null,"reflexes":null,"speed":63}},{"id":7900,"resourceId":226436,"resourceBaseId":226436,"futBinId":31732,"futWizId":9359,"firstName":"Hidde","lastName":"ter Avest","name":"Hidde ter Avest","commonName":"ter Avest","height":182,"weight":0,"birthDate":"1997-05-20","age":25,"league":10,"nation":34,"club":1903,"rarity":0,"traits":[],"specialities":[],"position":"RWB","skillMoves":2,"weakFoot":3,"foot":"Right","attackWorkRate":"Med","defenseWorkRate":"Med","totalStats":397,"totalStatsInGame":1807,"color":"silver","rating":71,"ratingAverage":66,"pace":72,"shooting":53,"passing":65,"dribbling":70,"defending":66,"physicality":71,"paceAttributes":{"acceleration":69,"sprintSpeed":74},"shootingAttributes":{"positioning":61,"finishing":59,"shotPower":64,"longShots":32,"volleys":33,"penalties":43},"passingAttributes":{"vision":61,"crossing":71,"freeKickAccuracy":29,"shortPassing":69,"longPassing":65,"curve":59},"dribblingAttributes":{"agility":65,"balance":65,"reactions":70,"ballControl":72,"dribbling":70,"composure":68},"defendingAttributes":{"interceptions":63,"headingAccuracy":63,"standingTackle":66,"slidingTackle":68,"defenseAwareness":68},"physicalityAttributes":{"jumping":67,"stamina":75,"strength":71,"aggression":67},"goalkeeperAttributes":{"diving":null,"handling":null,"kicking":null,"positioning":null,"reflexes":null,"speed":71}},{"id":8160,"resourceId":219736,"resourceBaseId":219736,"futBinId":30801,"futWizId":9654,"firstName":"Ethan","lastName":"Horvath","name":"Ethan Horvath","commonName":"Horvath","height":195,"weight":0,"birthDate":"1995-06-09","age":27,"league":14,"nation":95,"club":1923,"rarity":1,"traits":[],"specialities":[],"position":"GK","skillMoves":1,"weakFoot":3,"foot":"Right","attackWorkRate":"Med","defenseWorkRate":"Med","totalStats":387,"totalStatsInGame":833,"color":"silver","rating":71,"ratingAverage":64,"pace":48,"shooting":19,"passing":25,"dribbling":39,"defending":10,"physicality":46,"paceAttributes":{"acceleration":48,"sprintSpeed":49},"shootingAttributes":{"positioning":11,"finishing":17,"shotPower":43,"longShots":19,"volleys":14,"penalties":11},"passingAttributes":{"vision":50,"crossing":11,"freeKickAccuracy":17,"shortPassing":31,"longPassing":30,"curve":16},"dribblingAttributes":{"agility":54,"balance":32,"reactions":72,"ballControl":22,"dribbling":16,"composure":31},"defendingAttributes":{"interceptions":10,"headingAccuracy":13,"standingTackle":9,"slidingTackle":8,"defenseAwareness":14},"physicalityAttributes":{"jumping":64,"stamina":30,"strength":64,"aggression":27},"goalkeeperAttributes":{"diving":78,"handling":66,"kicking":57,"positioning":62,"reflexes":76,"speed":48}},{"id":8161,"resourceId":222156,"resourceBaseId":222156,"futBinId":31090,"futWizId":9605,"firstName":"James","lastName":"Bree","name":"James Bree","commonName":"Bree","height":178,"weight":0,"birthDate":"1997-12-11","age":25,"league":14,"nation":14,"club":1923,"rarity":0,"traits":[],"specialities":[],"position":"RWB","skillMoves":2,"weakFoot":3,"foot":"Right","attackWorkRate":"High","defenseWorkRate":"Med","totalStats":381,"totalStatsInGame":1773,"color":"silver","rating":71,"ratingAverage":63,"pace":73,"shooting":44,"passing":64,"dribbling":66,"defending":67,"physicality":67,"paceAttributes":{"acceleration":73,"sprintSpeed":73},"shootingAttributes":{"positioning":61,"finishing":38,"shotPower":54,"longShots":43,"volleys":36,"penalties":43},"passingAttributes":{"vision":55,"crossing":72,"freeKickAccuracy":68,"shortPassing":65,"longPassing":60,"curve":60},"dribblingAttributes":{"agility":66,"balance":61,"reactions":65,"ballControl":68,"dribbling":67,"composure":56},"defendingAttributes":{"interceptions":67,"headingAccuracy":59,"standingTackle":69,"slidingTackle":66,"defenseAwareness":69},"physicalityAttributes":{"jumping":62,"stamina":75,"strength":68,"aggression":54},"goalkeeperAttributes":{"diving":null,"handling":null,"kicking":null,"positioning":null,"reflexes":null,"speed":73}}]}