{"pagination":{"countCurrent":20,"countTotal":17965,"pageCurrent":35,"pageTotal":899,"itemsPerPage":20},"items":[{"id":17677,"resourceId":50553725,"resourceBaseId":222077,"futBinId":52387,"futWizId":null,"firstName":null,"lastName":null,"name":"Manuel Locatelli","commonName":"Locatelli","height":185,"weight":75,"birthDate":"1998-01-08","age":25,"league":31,"nation":27,"club":45,"rarity":58,"traits":[{"id":2,"name":"Playmaker (CPU AI)"},{"id":10,"name":"Long Shot Taker (CPU AI)"}],"specialities":[],"position":"CDM","skillMoves":3,"weakFoot":4,"foot":"Right","attackWorkRate":"Med","defenseWorkRate":"High","totalStats":506,"totalStatsInGame":2401,"color":"gold","rating":87,"ratingAverage":84,"pace":79,"shooting":82,"passing":87,"dribbling":85,"defending":87,"physicality":86,"paceAttributes":{"acceleration":78,"sprintSpeed":79},"shootingAttributes":{"positioning":81,"finishing":79,"shotPower":87,"longShots":89,"volleys":70,"penalties":66},"passingAttributes":{"vision":91,"crossing":78,"freeKickAccuracy":73,"shortPassing":90,"longPassing":90,"curve":81},"dribblingAttributes":{"agility":81,"balance":82,"reactions":89,"ballControl":87,"dribbling":84,"composure":85},"defendingAttributes":{"interceptions":88,"headingAccuracy":73,"standingTackle":89,"slidingTackle":85,"defenseAwareness":89},"physicalityAttributes":{"jumping":76,"stamina":92,"strength":84,"aggression":85},"goalkeeperAttributes":{"diving":null,"handling":null,"kicking":null,"positioning":null,"reflexes":null,"speed":78}},{"id":17678,"resourceId":67337443,"resourceBaseId":228579,"futBinId":52390,"futWizId":21242,"firstName":"Benjamin","lastName":"Henrichs","name":"Benjamin Henrichs","commonName":"Henrichs","height":185,"weight":79,"birthDate":"1997-02-23","age":26,"league":19,"nation":21,"club":112172,"rarity":58,"traits":[{"id":21,"name":"Injury Prone"}],"specialities":[],"position":"RWB","skillMoves":3,"weakFoot":4,"foot":"Right","attackWorkRate":"High","defenseWorkRate":"Med","totalStats":489,"totalStatsInGame":2300,"color":"gold","rating":87,"ratingAverage":81,"pace":90,"shooting":63,"passing":81,"dribbling":87,"defending":85,"physicality":83,"paceAttributes":{"acceleration":94,"sprintSpeed":87},"shootingAttributes":{"positioning":74,"finishing":59,"shotPower":74,"longShots":55,"volleys":63,"penalties":70},"passingAttributes":{"vision":80,"crossing":86,"freeKickAccuracy":55,"shortPassing":86,"longPassing":74,"curve":82},"dribblingAttributes":{"agility":86,"balance":79,"reactions":87,"ballControl":88,"dribbling":88,"composure":86},"defendingAttributes":{"interceptions":86,"headingAccuracy":73,"standingTackle":87,"slidingTackle":87,"defenseAwareness":85},"physicalityAttributes":{"jumping":78,"stamina":89,"strength":81,"aggression":81},"goalkeeperAttributes":{"diving":null,"handling":null,"kicking":null,"positioning":null,"reflexes":null,"speed":90}},{"id":17679,"resourceId":50597680,"resourceBaseId":266032,"futBinId":52389,"futWizId":21241,"firstName":"Jamie","lastName":"Bynoe-Gittens","name":"Jamie Bynoe-Gittens","commonName":"Bynoe-Gittens","height":175,"weight":70,"birthDate":"2004-08-08","age":18,"league":19,"nation":14,"club":22,"rarity":58,"traits":[{"id":6,"name":"Speed Dribbler (CPU AI)"},{"id":8,"name":"Flair"}],"specialities":[],"position":"LM","skillMoves":4,"weakFoot":4,"foot":"Right","attackWorkRate":"High","defenseWorkRate":"Med","totalStats":460,"totalStatsInGame":2208,"color":"gold","rating":87,"ratingAverage":76,"pace":92,"shooting":84,"passing":82,"dribbling":90,"defending":40,"physicality":72,"paceAttributes":{"acceleration":96,"sprintSpeed":89},"shootingAttributes":{"positioning":84,"finishing":89,"shotPower":80,"longShots":77,"volleys":85,"penalties":77},"passingAttributes":{"vision":77,"crossing":84,"freeKickAccuracy":60,"shortPassing":90,"longPassing":75,"curve":84},"dribblingAttributes":{"agility":96,"balance":95,"reactions":84,"ballControl":88,"dribbling":91,"composure":84},"defendingAttributes":{"interceptions":40,"headingAccuracy":70,"standingTackle":37,"slidingTackle":40,"defenseAwareness":33},"physicalityAttributes":{"jumping":95,"stamina":85,"strength":71,"aggression":52},"goalkeeperAttributes":{"diving":null,"handling":null,"kicking":null,"positioning":null,"reflexes":null,"speed":92}},{"id":17681,"resourceId":50552150,"resourceBaseId":220502,"futBinId":52396,"futWizId":21243,"firstName":"Mattia","lastName":"Zaccagni","name":"Mattia Zaccagni","commonName":"Zaccagni","height":177,"weight":63,"birthDate":"1995-06-16","age":27,"league":31,"nation":27,"club":115841,"rarity":58,"traits":[{"id":1,"name":"Technical Dribbler (CPU AI)"},{"id":8,"name":"Flair"},{"id":9,"name":"Outside Foot Shot"}],"specialities":[],"position":"LW","skillMoves":4,"weakFoot":4,"foot":"Right","attackWorkRate":"High","defenseWorkRate":"Med","totalStats":496,"totalStatsInGame":2328,"color":"gold","rating":87,"ratingAverage":80,"pace":90,"shooting":82,"passing":83,"dribbling":91,"defending":65,"physicality":73,"paceAttributes":{"acceleration":95,"sprintSpeed":90},"shootingAttributes":{"positioning":90,"finishing":84,"shotPower":86,"longShots":83,"volleys":76,"penalties":72},"passingAttributes":{"vision":87,"crossing":82,"freeKickAccuracy":59,"shortPassing":89,"longPassing":87,"curve":79},"dribblingAttributes":{"agility":96,"balance":94,"reactions":86,"ballControl":92,"dribbling":95,"composure":82},"defendingAttributes":{"interceptions":68,"headingAccuracy":77,"standingTackle":68,"slidingTackle":61,"defenseAwareness":65},"physicalityAttributes":{"jumping":54,"stamina":85,"strength":74,"aggression":72},"goalkeeperAttributes":{"diving":null,"handling":null,"kicking":null,"positioning":null,"reflexes":null,"speed":92}},{"id":17682,"resourceId":50573038,"resourceBaseId":241390,"futBinId":52395,"futWizId":21244,"firstName":"Eljif","lastName":"Elmas","name":"Eljif Elmas","commonName":"Elmas","height":184,"weight":74,"birthDate":"1999-09-24","age":23,"league":31,"nation":19,"club":116365,"rarity":58,"traits":[{"id":1,"name":"Technical Dribbler (CPU AI)"},{"id":8,"name":"Flair"},{"id":9,"name":"Outside Foot Shot"}],"specialities":[],"position":"CAM","skillMoves":4,"weakFoot":4,"foot":"Right","attackWorkRate":"Med","defenseWorkRate":"Med","totalStats":500,"totalStatsInGame":2326,"color":"gold","rating":87,"ratingAverage":83,"pace":86,"shooting":81,"passing":85,"dribbling":92,"defending":76,"physicality":80,"paceAttributes":{"acceleration":87,"sprintSpeed":85},"shootingAttributes":{"positioning":82,"finishing":80,"shotPower":90,"longShots":84,"volleys":64,"penalties":66},"passingAttributes":{"vision":85,"crossing":77,"freeKickAccuracy":62,"shortPassing":93,"longPassing":88,"curve":75},"dribblingAttributes":{"agility":93,"balance":82,"reactions":81,"ballControl":94,"dribbling":95,"composure":82},"defendingAttributes":{"interceptions":80,"headingAccuracy":67,"standingTackle":83,"slidingTackle":74,"defenseAwareness":71},"physicalityAttributes":{"jumping":54,"stamina":88,"strength":75,"aggression":89},"goalkeeperAttributes":{"diving":null,"handling":null,"kicking":null,"positioning":null,"reflexes":null,"speed":86}},{"id":17685,"resourceId":117667748,"resourceBaseId":227236,"futBinId":52401,"futWizId":21253,"firstName":"André-Franck","lastName":"Zambo Anguissa","name":"Zambo Anguissa","commonName":"Zambo Anguissa","height":184,"weight":78,"birthDate":"1995-11-16","age":27,"league":31,"nation":103,"club":116365,"rarity":3,"traits":[{"id":1,"name":"Technical Dribbler (CPU AI)"},{"id":8,"name":"Flair"}],"specialities":[],"position":"CM","skillMoves":3,"weakFoot":3,"foot":"Right","attackWorkRate":"Med","defenseWorkRate":"Low","totalStats":507,"totalStatsInGame":2361,"color":"gold","rating":87,"ratingAverage":84,"pace":85,"shooting":78,"passing":80,"dribbling":87,"defending":87,"physicality":90,"paceAttributes":{"acceleration":84,"sprintSpeed":85},"shootingAttributes":{"positioning":91,"finishing":76,"shotPower":85,"longShots":79,"volleys":62,"penalties":69},"passingAttributes":{"vision":85,"crossing":66,"freeKickAccuracy":51,"shortPassing":90,"longPassing":83,"curve":66},"dribblingAttributes":{"agility":82,"balance":83,"reactions":87,"ballControl":88,"dribbling":88,"composure":88},"defendingAttributes":{"interceptions":89,"headingAccuracy":76,"standingTackle":94,"slidingTackle":78,"defenseAwareness":85},"physicalityAttributes":{"jumping":81,"stamina":90,"strength":91,"aggression":89},"goalkeeperAttributes":{"diving":null,"handling":null,"kicking":null,"positioning":null,"reflexes":null,"speed":84}},{"id":17686,"resourceId":100898369,"resourceBaseId":235073,"futBinId":52402,"futWizId":21251,"firstName":"Gregor","lastName":"Kobel","name":"Gregor Kobel","commonName":"Kobel","height":195,"weight":88,"birthDate":"1997-12-06","age":25,"league":19,"nation":47,"club":22,"rarity":3,"traits":[{"id":18,"name":"Comes for Crosses"},{"id":19,"name":"GK Long Throw"},{"id":22,"name":"Leadership"},{"id":24,"name":"Rushes out of Goal"}],"specialities":[],"position":"GK","skillMoves":1,"weakFoot":3,"foot":"Right","attackWorkRate":"Med","defenseWorkRate":"Med","totalStats":477,"totalStatsInGame":920,"color":"gold","rating":87,"ratingAverage":79,"pace":0,"shooting":0,"passing":0,"dribbling":0,"defending":0,"physicality":0,"paceAttributes":{"acceleration":null,"sprintSpeed":null},"shootingAttributes":{"positioning":null,"finishing":null,"shotPower":null,"longShots":null,"volleys":null,"penalties":null},"passingAttributes":{"vision":null,"crossing":null,"freeKickAccuracy":null,"shortPassing":null,"longPassing":null,"curve":null},"dribblingAttributes":{"agility":null,"balance":null,"reactions":null,"ballControl":null,"dribbling":null,"composure":66},"defendingAttributes":{"interceptions":null,"headingAccuracy":null,"standingTackle":null,"slidingTackle":null,"defenseAwareness":null},"physicalityAttributes":{"jumping":null,"stamina":null,"strength":null,"aggression":null},"goalkeeperAttributes":{"diving":88,"handling":86,"kicking":79,"positioning":85,"reflexes":92,"speed":47}},{"id":17687,"resourceId":100900988,"resourceBaseId":237692,"futBinId":52403,"futWizId":21249,"firstName":"Phil","lastName":"Foden","name":"Phil Foden","commonName":"Foden","height":171,"weight":69,"birthDate":"2000-05-28","age":22,"league":13,"nation":14,"club":10,"rarity":3,"traits":[{"id":1,"name":"Technical Dribbler (CPU AI)"},{"id":2,"name":"Playmaker (CPU AI)"},{"id":8,"name":"Flair"},{"id":10,"name":"Long Shot Taker (CPU AI)"}],"specialities":[],"position":"RW","skillMoves":4,"weakFoot":3,"foot":"Left","attackWorkRate":"High","defenseWorkRate":"High","totalStats":460,"totalStatsInGame":2189,"color":"gold","rating":87,"ratingAverage":76,"pace":84,"shooting":81,"passing":84,"dribbling":90,"defending":58,"physicality":63,"paceAttributes":{"acceleration":88,"sprintSpeed":80},"shootingAttributes":{"positioning":85,"finishing":82,"shotPower":85,"longShots":80,"volleys":61,"penalties":66},"passingAttributes":{"vision":88,"crossing":79,"freeKickAccuracy":71,"shortPassing":88,"longPassing":84,"curve":76},"dribblingAttributes":{"agility":93,"balance":93,"reactions":85,"ballControl":93,"dribbling":89,"composure":86},"defendingAttributes":{"interceptions":61,"headingAccuracy":49,"standingTackle":61,"slidingTackle":49,"defenseAwareness":60},"physicalityAttributes":{"jumping":52,"stamina":87,"strength":50,"aggression":68},"goalkeeperAttributes":{"diving":null,"handling":null,"kicking":null,"positioning":null,"reflexes":null,"speed":84}},{"id":17688,"resourceId":84120458,"resourceBaseId":234378,"futBinId":52404,"futWizId":21252,"firstName":"Declan","lastName":"Rice","name":"Declan Rice","commonName":"Rice","height":185,"weight":80,"birthDate":"1999-01-14","age":24,"league":13,"nation":14,"club":19,"rarity":3,"traits":[{"id":7,"name":"Long Passer (CPU AI)"},{"id":22,"name":"Leadership"}],"specialities":[],"position":"CDM","skillMoves":2,"weakFoot":3,"foot":"Right","attackWorkRate":"Med","defenseWorkRate":"High","totalStats":472,"totalStatsInGame":2210,"color":"gold","rating":87,"ratingAverage":78,"pace":75,"shooting":67,"passing":77,"dribbling":80,"defending":86,"physicality":87,"paceAttributes":{"acceleration":72,"sprintSpeed":78},"shootingAttributes":{"positioning":61,"finishing":64,"shotPower":77,"longShots":68,"volleys":52,"penalties":74},"passingAttributes":{"vision":82,"crossing":57,"freeKickAccuracy":60,"shortPassing":86,"longPassing":87,"curve":60},"dribblingAttributes":{"agility":58,"balance":71,"reactions":85,"ballControl":83,"dribbling":82,"composure":87},"defendingAttributes":{"interceptions":89,"headingAccuracy":76,"standingTackle":88,"slidingTackle":84,"defenseAwareness":86},"physicalityAttributes":{"jumping":78,"stamina":94,"strength":83,"aggression":88},"goalkeeperAttributes":{"diving":null,"handling":null,"kicking":null,"positioning":null,"reflexes":null,"speed":75}},{"id":17707,"resourceId":50537733,"resourceBaseId":206085,"futBinId":52398,"futWizId":21250,"firstName":"Jacob","lastName":"Murphy","name":"Jacob Murphy","commonName":"Murphy","height":179,"weight":74,"birthDate":"1995-02-24","age":28,"league":13,"nation":14,"club":13,"rarity":58,"traits":[{"id":10,"name":"Long Shot Taker (CPU AI)"}],"specialities":[],"position":"RM","skillMoves":4,"weakFoot":4,"foot":"Right","attackWorkRate":"High","defenseWorkRate":"Med","totalStats":500,"totalStatsInGame":2346,"color":"gold","rating":87,"ratingAverage":83,"pace":92,"shooting":80,"passing":84,"dribbling":88,"defending":78,"physicality":78,"paceAttributes":{"acceleration":91,"sprintSpeed":93},"shootingAttributes":{"positioning":84,"finishing":78,"shotPower":88,"longShots":82,"volleys":60,"penalties":78},"passingAttributes":{"vision":84,"crossing":88,"freeKickAccuracy":80,"shortPassing":84,"longPassing":80,"curve":88},"dribblingAttributes":{"agility":90,"balance":88,"reactions":84,"ballControl":88,"dribbling":88,"composure":84},"defendingAttributes":{"interceptions":80,"headingAccuracy":56,"standingTackle":85,"slidingTackle":68,"defenseAwareness":80},"physicalityAttributes":{"jumping":60,"stamina":94,"strength":75,"aggression":68},"goalkeeperAttributes":{"diving":null,"handling":null,"kicking":null,"positioning":null,"reflexes":null,"speed":92}},{"id":17708,"resourceId":67312438,"resourceBaseId":203574,"futBinId":52397,"futWizId":21248,"firstName":"John","lastName":"Stones","name":"John Stones","commonName":"Stones","height":188,"weight":76,"birthDate":"1994-05-28","age":28,"league":13,"nation":14,"club":10,"rarity":58,"traits":[{"id":17,"name":"Long Throw-In"}],"specialities":[],"position":"CB","skillMoves":3,"weakFoot":4,"foot":"Right","attackWorkRate":"High","defenseWorkRate":"High","totalStats":469,"totalStatsInGame":2180,"color":"gold","rating":87,"ratingAverage":78,"pace":82,"shooting":55,"passing":78,"dribbling":81,"defending":88,"physicality":85,"paceAttributes":{"acceleration":78,"sprintSpeed":85},"shootingAttributes":{"positioning":56,"finishing":56,"shotPower":59,"longShots":48,"volleys":48,"penalties":57},"passingAttributes":{"vision":80,"crossing":65,"freeKickAccuracy":39,"shortPassing":88,"longPassing":84,"curve":80},"dribblingAttributes":{"agility":70,"balance":70,"reactions":86,"ballControl":88,"dribbling":78,"composure":84},"defendingAttributes":{"interceptions":88,"headingAccuracy":88,"standingTackle":88,"slidingTackle":88,"defenseAwareness":88},"physicalityAttributes":{"jumping":88,"stamina":83,"strength":86,"aggression":84},"goalkeeperAttributes":{"diving":null,"handling":null,"kicking":null,"positioning":null,"reflexes":null,"speed":81}},{"id":17728,"resourceId":67319981,"resourceBaseId":211117,"futBinId":52525,"futWizId":21292,"firstName":"Dele","lastName":"Alli","name":"Dele Alli","commonName":"Alli","height":188,"weight":80,"birthDate":"1996-04-11","age":26,"league":68,"nation":14,"club":327,"rarity":134,"traits":[{"id":1,"name":"Technical Dribbler (CPU AI)"},{"id":8,"name":"Flair"},{"id":9,"name":"Outside Foot Shot"}],"specialities":[],"position":"CAM","skillMoves":4,"weakFoot":4,"foot":"Right","attackWorkRate":"Med","defenseWorkRate":"Med","totalStats":505,"totalStatsInGame":2425,"color":"gold","rating":87,"ratingAverage":84,"pace":85,"shooting":87,"passing":85,"dribbling":89,"defending":76,"physicality":83,"paceAttributes":{"acceleration":82,"sprintSpeed":87},"shootingAttributes":{"positioning":90,"finishing":90,"shotPower":86,"longShots":81,"volleys":87,"penalties":90},"passingAttributes":{"vision":87,"crossing":79,"freeKickAccuracy":68,"shortPassing":90,"longPassing":86,"curve":86},"dribblingAttributes":{"agility":84,"balance":80,"reactions":86,"ballControl":92,"dribbling":90,"composure":89},"defendingAttributes":{"interceptions":74,"headingAccuracy":90,"standingTackle":75,"slidingTackle":72,"defenseAwareness":76},"physicalityAttributes":{"jumping":81,"stamina":83,"strength":86,"aggression":78},"goalkeeperAttributes":{"diving":null,"handling":null,"kicking":null,"positioning":null,"reflexes":null,"speed":84}},{"id":17729,"resourceId":67349617,"resourceBaseId":240753,"futBinId":52524,"futWizId":21293,"firstName":"Amine","lastName":"Gouiri","name":"Amine Gouiri","commonName":"Gouiri","height":180,"weight":72,"birthDate":"2000-02-16","age":23,"league":16,"nation":18,"club":74,"rarity":134,"traits":[{"id":3,"name":"Finesse Shot"},{"id":8,"name":"Flair"},{"id":9,"name":"Outside Foot Shot"}],"specialities":[],"position":"LM","skillMoves":4,"weakFoot":3,"foot":"Right","attackWorkRate":"High","defenseWorkRate":"Med","totalStats":504,"totalStatsInGame":2400,"color":"gold","rating":87,"ratingAverage":84,"pace":91,"shooting":87,"passing":85,"dribbling":89,"defending":72,"physicality":80,"paceAttributes":{"acceleration":95,"sprintSpeed":88},"shootingAttributes":{"positioning":88,"finishing":87,"shotPower":87,"longShots":88,"volleys":84,"penalties":84},"passingAttributes":{"vision":85,"crossing":85,"freeKickAccuracy":85,"shortPassing":88,"longPassing":77,"curve":87},"dribblingAttributes":{"agility":85,"balance":80,"reactions":86,"ballControl":89,"dribbling":91,"composure":87},"defendingAttributes":{"interceptions":74,"headingAccuracy":84,"standingTackle":69,"slidingTackle":55,"defenseAwareness":76},"physicalityAttributes":{"jumping":80,"stamina":83,"strength":82,"aggression":71},"goalkeeperAttributes":{"diving":null,"handling":null,"kicking":null,"positioning":null,"reflexes":null,"speed":91}},{"id":17730,"resourceId":50552299,"resourceBaseId":220651,"futBinId":52523,"futWizId":21291,"firstName":"José Ángel","lastName":"Esmoris Tasende","name":"Angeliño","commonName":"Angeliño","height":171,"weight":69,"birthDate":"1997-01-04","age":26,"league":19,"nation":45,"club":10029,"rarity":134,"traits":[{"id":1,"name":"Technical Dribbler (CPU AI)"},{"id":8,"name":"Flair"},{"id":9,"name":"Outside Foot Shot"},{"id":10,"name":"Long Shot Taker (CPU AI)"},{"id":15,"name":"Early Crosser"}],"specialities":[],"position":"LWB","skillMoves":4,"weakFoot":3,"foot":"Left","attackWorkRate":"High","defenseWorkRate":"High","totalStats":503,"totalStatsInGame":2403,"color":"gold","rating":87,"ratingAverage":83,"pace":89,"shooting":75,"passing":86,"dribbling":90,"defending":85,"physicality":78,"paceAttributes":{"acceleration":92,"sprintSpeed":87},"shootingAttributes":{"positioning":83,"finishing":74,"shotPower":85,"longShots":73,"volleys":67,"penalties":58},"passingAttributes":{"vision":86,"crossing":92,"freeKickAccuracy":80,"shortPassing":85,"longPassing":85,"curve":87},"dribblingAttributes":{"agility":90,"balance":90,"reactions":86,"ballControl":90,"dribbling":90,"composure":85},"defendingAttributes":{"interceptions":89,"headingAccuracy":70,"standingTackle":86,"slidingTackle":84,"defenseAwareness":86},"physicalityAttributes":{"jumping":80,"stamina":91,"strength":71,"aggression":81},"goalkeeperAttributes":{"diving":null,"handling":null,"kicking":null,"positioning":null,"reflexes":null,"speed":89}},{"id":17750,"resourceId":117662504,"resourceBaseId":221992,"futBinId":52543,"futWizId":21302,"firstName":"Hirving","lastName":"Lozano","name":"Hirving Lozano","commonName":"Lozano","height":175,"weight":70,"birthDate":"1995-07-30","age":27,"league":31,"nation":83,"club":116365,"rarity":8,"traits":[{"id":6,"name":"Speed Dribbler (CPU AI)"},{"id":9,"name":"Outside Foot Shot"}],"specialities":[],"position":"RW","skillMoves":4,"weakFoot":3,"foot":"Right","attackWorkRate":"High","defenseWorkRate":"Low","totalStats":468,"totalStatsInGame":2244,"color":"gold","rating":87,"ratingAverage":78,"pace":97,"shooting":84,"passing":80,"dribbling":88,"defending":49,"physicality":70,"paceAttributes":{"acceleration":96,"sprintSpeed":97},"shootingAttributes":{"positioning":91,"finishing":85,"shotPower":84,"longShots":83,"volleys":82,"penalties":81},"passingAttributes":{"vision":82,"crossing":81,"freeKickAccuracy":72,"shortPassing":82,"longPassing":72,"curve":80},"dribblingAttributes":{"agility":96,"balance":88,"reactions":87,"ballControl":86,"dribbling":89,"composure":80},"defendingAttributes":{"interceptions":54,"headingAccuracy":74,"standingTackle":42,"slidingTackle":35,"defenseAwareness":50},"physicalityAttributes":{"jumping":76,"stamina":86,"strength":61,"aggression":72},"goalkeeperAttributes":{"diving":null,"handling":null,"kicking":null,"positioning":null,"reflexes":null,"speed":96}},{"id":17751,"resourceId":100847194,"resourceBaseId":183898,"futBinId":52542,"futWizId":21301,"firstName":"Ángel","lastName":"Di María","name":"Ángel Di María","commonName":"Di María","height":180,"weight":69,"birthDate":"1988-02-14","age":35,"league":31,"nation":52,"club":45,"rarity":8,"traits":[{"id":1,"name":"Technical Dribbler (CPU AI)"},{"id":5,"name":"Chip Shot (CPU AI)"},{"id":8,"name":"Flair"},{"id":9,"name":"Outside Foot Shot"},{"id":10,"name":"Long Shot Taker (CPU AI)"}],"specialities":[],"position":"RW","skillMoves":5,"weakFoot":2,"foot":"Left","attackWorkRate":"High","defenseWorkRate":"Med","totalStats":467,"totalStatsInGame":2285,"color":"gold","rating":87,"ratingAverage":77,"pace":83,"shooting":83,"passing":87,"dribbling":90,"defending":51,"physicality":73,"paceAttributes":{"acceleration":84,"sprintSpeed":82},"shootingAttributes":{"positioning":86,"finishing":80,"shotPower":87,"longShots":88,"volleys":82,"penalties":77},"passingAttributes":{"vision":90,"crossing":88,"freeKickAccuracy":91,"shortPassing":85,"longPassing":83,"curve":95},"dribblingAttributes":{"agility":94,"balance":78,"reactions":86,"ballControl":90,"dribbling":91,"composure":89},"defendingAttributes":{"interceptions":45,"headingAccuracy":54,"standingTackle":58,"slidingTackle":55,"defenseAwareness":44},"physicalityAttributes":{"jumping":76,"stamina":81,"strength":66,"aggression":80},"goalkeeperAttributes":{"diving":null,"handling":null,"kicking":null,"positioning":null,"reflexes":null,"speed":83}},{"id":17752,"resourceId":67341296,"resourceBaseId":232432,"futBinId":52541,"futWizId":21300,"firstName":"Luka","lastName":"Jović","name":"Luka Jovic","commonName":"Jovic","height":182,"weight":85,"birthDate":"1997-12-23","age":25,"league":31,"nation":51,"club":110374,"rarity":8,"traits":[{"id":5,"name":"Chip Shot (CPU AI)"},{"id":9,"name":"Outside Foot Shot"}],"specialities":[],"position":"ST","skillMoves":3,"weakFoot":5,"foot":"Right","attackWorkRate":"Med","defenseWorkRate":"Med","totalStats":456,"totalStatsInGame":2196,"color":"gold","rating":87,"ratingAverage":76,"pace":87,"shooting":88,"passing":77,"dribbling":86,"defending":35,"physicality":83,"paceAttributes":{"acceleration":85,"sprintSpeed":89},"shootingAttributes":{"positioning":91,"finishing":89,"shotPower":93,"longShots":84,"volleys":93,"penalties":73},"passingAttributes":{"vision":79,"crossing":75,"freeKickAccuracy":62,"shortPassing":82,"longPassing":69,"curve":87},"dribblingAttributes":{"agility":83,"balance":86,"reactions":88,"ballControl":88,"dribbling":86,"composure":86},"defendingAttributes":{"interceptions":28,"headingAccuracy":95,"standingTackle":31,"slidingTackle":19,"defenseAwareness":30},"physicalityAttributes":{"jumping":85,"stamina":83,"strength":87,"aggression":70},"goalkeeperAttributes":{"diving":null,"handling":null,"kicking":null,"positioning":null,"reflexes":null,"speed":87}},{"id":17762,"resourceId":100907408,"resourceBaseId":244112,"futBinId":52559,"futWizId":21319,"firstName":"Daniel-Kofi","lastName":"Kyereh","name":"Daniel-Kofi Kyereh","commonName":"Kyereh","height":179,"weight":73,"birthDate":"1996-03-08","age":27,"league":19,"nation":117,"club":25,"rarity":97,"traits":[{"id":6,"name":"Speed Dribbler (CPU AI)"},{"id":8,"name":"Flair"}],"specialities":[],"position":"LW","skillMoves":5,"weakFoot":3,"foot":"Right","attackWorkRate":"Med","defenseWorkRate":"Med","totalStats":457,"totalStatsInGame":2192,"color":"gold","rating":87,"ratingAverage":76,"pace":93,"shooting":84,"passing":80,"dribbling":90,"defending":36,"physicality":74,"paceAttributes":{"acceleration":97,"sprintSpeed":90},"shootingAttributes":{"positioning":86,"finishing":90,"shotPower":83,"longShots":80,"volleys":80,"penalties":61},"passingAttributes":{"vision":86,"crossing":71,"freeKickAccuracy":73,"shortPassing":87,"longPassing":75,"curve":73},"dribblingAttributes":{"agility":97,"balance":95,"reactions":83,"ballControl":88,"dribbling":90,"composure":80},"defendingAttributes":{"interceptions":36,"headingAccuracy":89,"standingTackle":23,"slidingTackle":26,"defenseAwareness":36},"physicalityAttributes":{"jumping":97,"stamina":90,"strength":70,"aggression":60},"goalkeeperAttributes":{"diving":null,"handling":null,"kicking":null,"positioning":null,"reflexes":null,"speed":93}},{"id":17766,"resourceId":84098270,"resourceBaseId":212190,"futBinId":52563,"futWizId":21324,"firstName":"Niklas","lastName":"Süle","name":"Niklas Süle","commonName":"Süle","height":195,"weight":99,"birthDate":"1995-09-03","age":27,"league":19,"nation":21,"club":22,"rarity":3,"traits":[{"id":21,"name":"Injury Prone"}],"specialities":[],"position":"CB","skillMoves":3,"weakFoot":3,"foot":"Right","attackWorkRate":"Med","defenseWorkRate":"Med","totalStats":427,"totalStatsInGame":1931,"color":"gold","rating":87,"ratingAverage":71,"pace":75,"shooting":50,"passing":69,"dribbling":61,"defending":87,"physicality":85,"paceAttributes":{"acceleration":63,"sprintSpeed":85},"shootingAttributes":{"positioning":44,"finishing":31,"shotPower":81,"longShots":65,"volleys":49,"penalties":34},"passingAttributes":{"vision":69,"crossing":50,"freeKickAccuracy":40,"shortPassing":83,"longPassing":81,"curve":35},"dribblingAttributes":{"agility":35,"balance":45,"reactions":85,"ballControl":66,"dribbling":59,"composure":85},"defendingAttributes":{"interceptions":83,"headingAccuracy":86,"standingTackle":91,"slidingTackle":89,"defenseAwareness":85},"physicalityAttributes":{"jumping":61,"stamina":67,"strength":96,"aggression":88},"goalkeeperAttributes":{"diving":null,"handling":null,"kicking":null,"positioning":null,"reflexes":null,"speed":74}},{"id":17805,"resourceId":84141645,"resourceBaseId":255565,"futBinId":52612,"futWizId":21362,"firstName":"Kaoru","lastName":"Mitoma","name":"Kaoru Mitoma","commonName":"Mitoma","height":178,"weight":71,"birthDate":"1997-05-20","age":25,"league":13,"nation":163,"club":1808,"rarity":134,"traits":[{"id":1,"name":"Technical Dribbler (CPU AI)"},{"id":9,"name":"Outside Foot Shot"}],"specialities":[],"position":"LM","skillMoves":4,"weakFoot":3,"foot":"Right","attackWorkRate":"Med","defenseWorkRate":"Med","totalStats":495,"totalStatsInGame":2330,"color":"gold","rating":87,"ratingAverage":82,"pace":93,"shooting":83,"passing":83,"dribbling":90,"defending":69,"physicality":77,"paceAttributes":{"acceleration":96,"sprintSpeed":90},"shootingAttributes":{"positioning":82,"finishing":87,"shotPower":80,"longShots":81,"volleys":78,"penalties":74},"passingAttributes":{"vision":83,"crossing":80,"freeKickAccuracy":75,"shortPassing":88,"longPassing":80,"curve":80},"dribblingAttributes":{"agility":97,"balance":82,"reactions":85,"ballControl":90,"dribbling":91,"composure":85},"defendingAttributes":{"interceptions":70,"headingAccuracy":55,"standingTackle":73,"slidingTackle":67,"defenseAwareness":69},"physicalityAttributes":{"jumping":81,"stamina":84,"strength":75,"aggression":72},"goalkeeperAttributes":{"diving":null,"handling":null,"kicking":null,"positioning":null,"reflexes":null,"speed":93}}]}