{"pagination":{"countCurrent":20,"countTotal":17965,"pageCurrent":211,"pageTotal":899,"itemsPerPage":20},"items":[{"id":12809,"resourceId":225356,"resourceBaseId":225356,"futBinId":31577,"futWizId":8201,"firstName":"Andrés","lastName":"Ibargüen","name":"Andrés Ibargüen","commonName":"Ibargüen","height":168,"weight":0,"birthDate":"1992-05-07","age":30,"league":1003,"nation":56,"club":111722,"rarity":53,"traits":[],"specialities":[],"position":"LM","skillMoves":3,"weakFoot":3,"foot":"Right","attackWorkRate":"High","defenseWorkRate":"Med","totalStats":383,"totalStatsInGame":1808,"color":"silver","rating":73,"ratingAverage":63,"pace":91,"shooting":65,"passing":68,"dribbling":76,"defending":37,"physicality":46,"paceAttributes":{"acceleration":92,"sprintSpeed":90},"shootingAttributes":{"positioning":71,"finishing":66,"shotPower":63,"longShots":63,"volleys":55,"penalties":68},"passingAttributes":{"vision":72,"crossing":69,"freeKickAccuracy":52,"shortPassing":69,"longPassing":64,"curve":61},"dribblingAttributes":{"agility":91,"balance":82,"reactions":67,"ballControl":73,"dribbling":76,"composure":64},"defendingAttributes":{"interceptions":34,"headingAccuracy":52,"standingTackle":24,"slidingTackle":21,"defenseAwareness":51},"physicalityAttributes":{"jumping":83,"stamina":49,"strength":40,"aggression":46},"goalkeeperAttributes":{"diving":null,"handling":null,"kicking":null,"positioning":null,"reflexes":null,"speed":91}},{"id":13342,"resourceId":213815,"resourceBaseId":213815,"futBinId":30356,"futWizId":8349,"firstName":"Mikael","lastName":"Uhre","name":"Mikael Uhre","commonName":"Uhre","height":188,"weight":0,"birthDate":"1994-09-30","age":28,"league":39,"nation":13,"club":112134,"rarity":1,"traits":[],"specialities":[],"position":"ST","skillMoves":2,"weakFoot":4,"foot":"Right","attackWorkRate":"High","defenseWorkRate":"Med","totalStats":391,"totalStatsInGame":1758,"color":"silver","rating":73,"ratingAverage":65,"pace":89,"shooting":72,"passing":51,"dribbling":69,"defending":33,"physicality":77,"paceAttributes":{"acceleration":87,"sprintSpeed":91},"shootingAttributes":{"positioning":77,"finishing":76,"shotPower":75,"longShots":65,"volleys":62,"penalties":62},"passingAttributes":{"vision":62,"crossing":41,"freeKickAccuracy":32,"shortPassing":57,"longPassing":41,"curve":52},"dribblingAttributes":{"agility":75,"balance":55,"reactions":68,"ballControl":70,"dribbling":68,"composure":67},"defendingAttributes":{"interceptions":17,"headingAccuracy":65,"standingTackle":32,"slidingTackle":28,"defenseAwareness":37},"physicalityAttributes":{"jumping":72,"stamina":77,"strength":83,"aggression":64},"goalkeeperAttributes":{"diving":null,"handling":null,"kicking":null,"positioning":null,"reflexes":null,"speed":89}},{"id":12835,"resourceId":221875,"resourceBaseId":221875,"futBinId":31050,"futWizId":8056,"firstName":"Jun Ho","lastName":"Son","name":"Jun Ho Son","commonName":"Son Jun Ho","height":180,"weight":0,"birthDate":"1992-05-12","age":30,"league":2012,"nation":167,"club":111724,"rarity":0,"traits":[],"specialities":[],"position":"CDM","skillMoves":3,"weakFoot":3,"foot":"Right","attackWorkRate":"Med","defenseWorkRate":"Med","totalStats":414,"totalStatsInGame":1966,"color":"silver","rating":73,"ratingAverage":69,"pace":70,"shooting":62,"passing":69,"dribbling":70,"defending":67,"physicality":76,"paceAttributes":{"acceleration":65,"sprintSpeed":74},"shootingAttributes":{"positioning":65,"finishing":56,"shotPower":68,"longShots":72,"volleys":47,"penalties":64},"passingAttributes":{"vision":72,"crossing":51,"freeKickAccuracy":66,"shortPassing":76,"longPassing":75,"curve":61},"dribblingAttributes":{"agility":82,"balance":80,"reactions":67,"ballControl":70,"dribbling":68,"composure":60},"defendingAttributes":{"interceptions":74,"headingAccuracy":58,"standingTackle":71,"slidingTackle":62,"defenseAwareness":63},"physicalityAttributes":{"jumping":68,"stamina":92,"strength":72,"aggression":67},"goalkeeperAttributes":{"diving":null,"handling":null,"kicking":null,"positioning":null,"reflexes":null,"speed":69}},{"id":13158,"resourceId":207790,"resourceBaseId":207790,"futBinId":29725,"futWizId":8344,"firstName":"Kaan","lastName":"Ayhan","name":"Kaan Ayhan","commonName":"Ayhan","height":184,"weight":0,"birthDate":"1994-11-10","age":28,"league":31,"nation":48,"club":111974,"rarity":1,"traits":[],"specialities":[],"position":"CB","skillMoves":3,"weakFoot":3,"foot":"Right","attackWorkRate":"High","defenseWorkRate":"Med","totalStats":393,"totalStatsInGame":1932,"color":"silver","rating":73,"ratingAverage":65,"pace":56,"shooting":53,"passing":69,"dribbling":67,"defending":73,"physicality":75,"paceAttributes":{"acceleration":58,"sprintSpeed":55},"shootingAttributes":{"positioning":50,"finishing":35,"shotPower":80,"longShots":71,"volleys":40,"penalties":45},"passingAttributes":{"vision":65,"crossing":65,"freeKickAccuracy":70,"shortPassing":72,"longPassing":68,"curve":79},"dribblingAttributes":{"agility":66,"balance":67,"reactions":73,"ballControl":71,"dribbling":63,"composure":75},"defendingAttributes":{"interceptions":75,"headingAccuracy":70,"standingTackle":73,"slidingTackle":70,"defenseAwareness":74},"physicalityAttributes":{"jumping":82,"stamina":67,"strength":77,"aggression":76},"goalkeeperAttributes":{"diving":null,"handling":null,"kicking":null,"positioning":null,"reflexes":null,"speed":56}},{"id":13159,"resourceId":241937,"resourceBaseId":241937,"futBinId":34091,"futWizId":8058,"firstName":"Abdou","lastName":"Harroui","name":"Abdou Harroui","commonName":"Harroui","height":182,"weight":0,"birthDate":"1998-01-13","age":25,"league":31,"nation":129,"club":111974,"rarity":1,"traits":[],"specialities":[],"position":"CDM","skillMoves":3,"weakFoot":5,"foot":"Right","attackWorkRate":"Med","defenseWorkRate":"Med","totalStats":429,"totalStatsInGame":2005,"color":"silver","rating":73,"ratingAverage":71,"pace":74,"shooting":68,"passing":70,"dribbling":75,"defending":67,"physicality":75,"paceAttributes":{"acceleration":75,"sprintSpeed":73},"shootingAttributes":{"positioning":68,"finishing":66,"shotPower":76,"longShots":74,"volleys":55,"penalties":45},"passingAttributes":{"vision":74,"crossing":66,"freeKickAccuracy":63,"shortPassing":74,"longPassing":68,"curve":60},"dribblingAttributes":{"agility":71,"balance":70,"reactions":71,"ballControl":77,"dribbling":76,"composure":72},"defendingAttributes":{"interceptions":68,"headingAccuracy":57,"standingTackle":71,"slidingTackle":66,"defenseAwareness":67},"physicalityAttributes":{"jumping":76,"stamina":85,"strength":73,"aggression":68},"goalkeeperAttributes":{"diving":null,"handling":null,"kicking":null,"positioning":null,"reflexes":null,"speed":74}},{"id":13160,"resourceId":200054,"resourceBaseId":200054,"futBinId":29056,"futWizId":8484,"firstName":"Pedro Mba","lastName":"Obiang Avomo","name":"Pedro Mba Obiang Avomo","commonName":"Pedro Obiang","height":185,"weight":0,"birthDate":"1992-03-27","age":31,"league":31,"nation":112,"club":111974,"rarity":1,"traits":[],"specialities":[],"position":"CDM","skillMoves":3,"weakFoot":3,"foot":"Right","attackWorkRate":"Med","defenseWorkRate":"Med","totalStats":400,"totalStatsInGame":1938,"color":"silver","rating":73,"ratingAverage":66,"pace":56,"shooting":59,"passing":70,"dribbling":70,"defending":74,"physicality":71,"paceAttributes":{"acceleration":57,"sprintSpeed":55},"shootingAttributes":{"positioning":60,"finishing":50,"shotPower":73,"longShots":65,"volleys":60,"penalties":59},"passingAttributes":{"vision":69,"crossing":68,"freeKickAccuracy":62,"shortPassing":74,"longPassing":70,"curve":56},"dribblingAttributes":{"agility":63,"balance":63,"reactions":68,"ballControl":72,"dribbling":70,"composure":75},"defendingAttributes":{"interceptions":73,"headingAccuracy":68,"standingTackle":76,"slidingTackle":74,"defenseAwareness":73},"physicalityAttributes":{"jumping":72,"stamina":71,"strength":72,"aggression":70},"goalkeeperAttributes":{"diving":null,"handling":null,"kicking":null,"positioning":null,"reflexes":null,"speed":56}},{"id":12905,"resourceId":216391,"resourceBaseId":216391,"futBinId":30640,"futWizId":8192,"firstName":"Erik","lastName":"Nascimento de Lima","name":"Erik Nascimento de Lima","commonName":"Erik","height":170,"weight":0,"birthDate":"1994-07-18","age":28,"league":2012,"nation":54,"club":111769,"rarity":1,"traits":[],"specialities":[],"position":"LM","skillMoves":3,"weakFoot":4,"foot":"Right","attackWorkRate":"Med","defenseWorkRate":"Med","totalStats":378,"totalStatsInGame":1806,"color":"silver","rating":73,"ratingAverage":63,"pace":86,"shooting":71,"passing":66,"dribbling":75,"defending":23,"physicality":57,"paceAttributes":{"acceleration":89,"sprintSpeed":83},"shootingAttributes":{"positioning":73,"finishing":72,"shotPower":72,"longShots":70,"volleys":71,"penalties":67},"passingAttributes":{"vision":65,"crossing":62,"freeKickAccuracy":63,"shortPassing":71,"longPassing":62,"curve":56},"dribblingAttributes":{"agility":89,"balance":83,"reactions":69,"ballControl":72,"dribbling":75,"composure":62},"defendingAttributes":{"interceptions":17,"headingAccuracy":64,"standingTackle":16,"slidingTackle":21,"defenseAwareness":22},"physicalityAttributes":{"jumping":81,"stamina":74,"strength":59,"aggression":26},"goalkeeperAttributes":{"diving":null,"handling":null,"kicking":null,"positioning":null,"reflexes":null,"speed":86}},{"id":13161,"resourceId":214622,"resourceBaseId":214622,"futBinId":30424,"futWizId":8250,"firstName":"Jeremy","lastName":"Toljan","name":"Jeremy Toljan","commonName":"Toljan","height":182,"weight":74,"birthDate":"1994-08-08","age":28,"league":31,"nation":21,"club":111974,"rarity":1,"traits":[],"specialities":[],"position":"RB","skillMoves":3,"weakFoot":4,"foot":"Right","attackWorkRate":"Med","defenseWorkRate":"Med","totalStats":393,"totalStatsInGame":1790,"color":"silver","rating":73,"ratingAverage":65,"pace":86,"shooting":42,"passing":63,"dribbling":69,"defending":66,"physicality":67,"paceAttributes":{"acceleration":85,"sprintSpeed":86},"shootingAttributes":{"positioning":56,"finishing":39,"shotPower":49,"longShots":38,"volleys":41,"penalties":39},"passingAttributes":{"vision":48,"crossing":75,"freeKickAccuracy":32,"shortPassing":70,"longPassing":63,"curve":61},"dribblingAttributes":{"agility":73,"balance":70,"reactions":67,"ballControl":71,"dribbling":68,"composure":58},"defendingAttributes":{"interceptions":68,"headingAccuracy":49,"standingTackle":72,"slidingTackle":71,"defenseAwareness":63},"physicalityAttributes":{"jumping":80,"stamina":71,"strength":65,"aggression":62},"goalkeeperAttributes":{"diving":null,"handling":null,"kicking":null,"positioning":null,"reflexes":null,"speed":85}},{"id":13201,"resourceId":216072,"resourceBaseId":216072,"futBinId":30595,"futWizId":8448,"firstName":"Gaetano","lastName":"Letizia","name":"Gaetano Letizia","commonName":"Letizia","height":173,"weight":0,"birthDate":"1990-06-29","age":32,"league":32,"nation":27,"club":112026,"rarity":1,"traits":[],"specialities":[],"position":"RB","skillMoves":3,"weakFoot":4,"foot":"Right","attackWorkRate":"High","defenseWorkRate":"High","totalStats":410,"totalStatsInGame":1927,"color":"silver","rating":73,"ratingAverage":68,"pace":87,"shooting":56,"passing":62,"dribbling":69,"defending":66,"physicality":70,"paceAttributes":{"acceleration":92,"sprintSpeed":83},"shootingAttributes":{"positioning":55,"finishing":45,"shotPower":74,"longShots":67,"volleys":51,"penalties":45},"passingAttributes":{"vision":49,"crossing":69,"freeKickAccuracy":44,"shortPassing":65,"longPassing":68,"curve":58},"dribblingAttributes":{"agility":84,"balance":88,"reactions":69,"ballControl":65,"dribbling":67,"composure":69},"defendingAttributes":{"interceptions":69,"headingAccuracy":54,"standingTackle":70,"slidingTackle":69,"defenseAwareness":64},"physicalityAttributes":{"jumping":80,"stamina":87,"strength":63,"aggression":64},"goalkeeperAttributes":{"diving":null,"handling":null,"kicking":null,"positioning":null,"reflexes":null,"speed":87}},{"id":13202,"resourceId":50572191,"resourceBaseId":240543,"futBinId":48262,"futWizId":8136,"firstName":"Maxime","lastName":"Leverbe","name":"Maxime Leverbe","commonName":"Leverbe","height":188,"weight":0,"birthDate":"1997-02-15","age":26,"league":32,"nation":18,"club":112026,"rarity":1,"traits":[],"specialities":[],"position":"CB","skillMoves":2,"weakFoot":2,"foot":"Right","attackWorkRate":"Med","defenseWorkRate":"High","totalStats":374,"totalStatsInGame":1726,"color":"silver","rating":73,"ratingAverage":62,"pace":66,"shooting":42,"passing":54,"dribbling":61,"defending":74,"physicality":77,"paceAttributes":{"acceleration":66,"sprintSpeed":66},"shootingAttributes":{"positioning":34,"finishing":41,"shotPower":58,"longShots":26,"volleys":39,"penalties":59},"passingAttributes":{"vision":51,"crossing":38,"freeKickAccuracy":38,"shortPassing":68,"longPassing":57,"curve":38},"dribblingAttributes":{"agility":59,"balance":63,"reactions":67,"ballControl":64,"dribbling":58,"composure":66},"defendingAttributes":{"interceptions":70,"headingAccuracy":72,"standingTackle":76,"slidingTackle":71,"defenseAwareness":77},"physicalityAttributes":{"jumping":76,"stamina":80,"strength":78,"aggression":70},"goalkeeperAttributes":{"diving":null,"handling":null,"kicking":null,"positioning":null,"reflexes":null,"speed":66}},{"id":13248,"resourceId":208451,"resourceBaseId":208451,"futBinId":29785,"futWizId":8206,"firstName":"Robin","lastName":"Quaison","name":"Robin Quaison","commonName":"Quaison","height":183,"weight":0,"birthDate":"1993-10-09","age":29,"league":350,"nation":46,"club":112096,"rarity":1,"traits":[],"specialities":[],"position":"CF","skillMoves":3,"weakFoot":3,"foot":"Right","attackWorkRate":"High","defenseWorkRate":"Med","totalStats":399,"totalStatsInGame":1926,"color":"silver","rating":73,"ratingAverage":66,"pace":71,"shooting":72,"passing":67,"dribbling":75,"defending":44,"physicality":70,"paceAttributes":{"acceleration":76,"sprintSpeed":66},"shootingAttributes":{"positioning":77,"finishing":72,"shotPower":74,"longShots":71,"volleys":76,"penalties":67},"passingAttributes":{"vision":65,"crossing":67,"freeKickAccuracy":56,"shortPassing":70,"longPassing":66,"curve":72},"dribblingAttributes":{"agility":75,"balance":75,"reactions":79,"ballControl":75,"dribbling":74,"composure":76},"defendingAttributes":{"interceptions":49,"headingAccuracy":54,"standingTackle":39,"slidingTackle":55,"defenseAwareness":39},"physicalityAttributes":{"jumping":56,"stamina":76,"strength":73,"aggression":56},"goalkeeperAttributes":{"diving":null,"handling":null,"kicking":null,"positioning":null,"reflexes":null,"speed":71}},{"id":13249,"resourceId":216247,"resourceBaseId":216247,"futBinId":30612,"futWizId":8198,"firstName":"Marcel","lastName":"Tisserand","name":"Marcel Tisserand","commonName":"Tisserand","height":185,"weight":0,"birthDate":"1993-01-10","age":30,"league":350,"nation":110,"club":112096,"rarity":1,"traits":[],"specialities":[],"position":"CB","skillMoves":3,"weakFoot":3,"foot":"Right","attackWorkRate":"High","defenseWorkRate":"Med","totalStats":415,"totalStatsInGame":1963,"color":"silver","rating":73,"ratingAverage":69,"pace":72,"shooting":58,"passing":69,"dribbling":69,"defending":72,"physicality":75,"paceAttributes":{"acceleration":74,"sprintSpeed":71},"shootingAttributes":{"positioning":63,"finishing":55,"shotPower":67,"longShots":57,"volleys":54,"penalties":56},"passingAttributes":{"vision":67,"crossing":69,"freeKickAccuracy":40,"shortPassing":73,"longPassing":72,"curve":70},"dribblingAttributes":{"agility":71,"balance":64,"reactions":75,"ballControl":71,"dribbling":68,"composure":65},"defendingAttributes":{"interceptions":74,"headingAccuracy":73,"standingTackle":73,"slidingTackle":71,"defenseAwareness":70},"physicalityAttributes":{"jumping":75,"stamina":75,"strength":76,"aggression":74},"goalkeeperAttributes":{"diving":null,"handling":null,"kicking":null,"positioning":null,"reflexes":null,"speed":72}},{"id":13022,"resourceId":258648,"resourceBaseId":258648,"futBinId":36907,"futWizId":8573,"firstName":"Carlos Augusto","lastName":"Zopolato Neves","name":"Carlos Augusto","commonName":"Carlos Augusto","height":184,"weight":0,"birthDate":"1999-01-07","age":24,"league":31,"nation":54,"club":111811,"rarity":1,"traits":[],"specialities":[],"position":"LWB","skillMoves":2,"weakFoot":2,"foot":"Left","attackWorkRate":"Med","defenseWorkRate":"High","totalStats":395,"totalStatsInGame":1849,"color":"silver","rating":73,"ratingAverage":65,"pace":67,"shooting":50,"passing":67,"dribbling":70,"defending":71,"physicality":70,"paceAttributes":{"acceleration":65,"sprintSpeed":68},"shootingAttributes":{"positioning":68,"finishing":49,"shotPower":51,"longShots":51,"volleys":47,"penalties":43},"passingAttributes":{"vision":64,"crossing":72,"freeKickAccuracy":37,"shortPassing":72,"longPassing":66,"curve":54},"dribblingAttributes":{"agility":69,"balance":54,"reactions":69,"ballControl":72,"dribbling":70,"composure":69},"defendingAttributes":{"interceptions":70,"headingAccuracy":73,"standingTackle":72,"slidingTackle":72,"defenseAwareness":70},"physicalityAttributes":{"jumping":67,"stamina":78,"strength":67,"aggression":70},"goalkeeperAttributes":{"diving":null,"handling":null,"kicking":null,"positioning":null,"reflexes":null,"speed":66}},{"id":13023,"resourceId":219594,"resourceBaseId":219594,"futBinId":30789,"futWizId":8574,"firstName":"Andrea","lastName":"Barberis","name":"Andrea Barberis","commonName":"Barberis","height":177,"weight":0,"birthDate":"1993-12-11","age":29,"league":31,"nation":27,"club":111811,"rarity":0,"traits":[],"specialities":[],"position":"CDM","skillMoves":2,"weakFoot":2,"foot":"Right","attackWorkRate":"High","defenseWorkRate":"High","totalStats":395,"totalStatsInGame":1911,"color":"silver","rating":73,"ratingAverage":65,"pace":74,"shooting":49,"passing":70,"dribbling":68,"defending":68,"physicality":66,"paceAttributes":{"acceleration":74,"sprintSpeed":74},"shootingAttributes":{"positioning":72,"finishing":38,"shotPower":59,"longShots":57,"volleys":56,"penalties":51},"passingAttributes":{"vision":66,"crossing":67,"freeKickAccuracy":68,"shortPassing":75,"longPassing":72,"curve":57},"dribblingAttributes":{"agility":73,"balance":71,"reactions":73,"ballControl":72,"dribbling":64,"composure":65},"defendingAttributes":{"interceptions":73,"headingAccuracy":48,"standingTackle":73,"slidingTackle":68,"defenseAwareness":67},"physicalityAttributes":{"jumping":64,"stamina":83,"strength":53,"aggression":78},"goalkeeperAttributes":{"diving":null,"handling":null,"kicking":null,"positioning":null,"reflexes":null,"speed":74}},{"id":13024,"resourceId":205089,"resourceBaseId":205089,"futBinId":29526,"futWizId":8555,"firstName":"Mattia","lastName":"Valoti","name":"Mattia Valoti","commonName":"Valoti","height":181,"weight":0,"birthDate":"1993-09-06","age":29,"league":31,"nation":27,"club":111811,"rarity":1,"traits":[],"specialities":[],"position":"CM","skillMoves":3,"weakFoot":3,"foot":"Right","attackWorkRate":"Med","defenseWorkRate":"Med","totalStats":388,"totalStatsInGame":1916,"color":"silver","rating":73,"ratingAverage":64,"pace":62,"shooting":70,"passing":75,"dribbling":75,"defending":54,"physicality":52,"paceAttributes":{"acceleration":61,"sprintSpeed":63},"shootingAttributes":{"positioning":71,"finishing":68,"shotPower":68,"longShots":73,"volleys":69,"penalties":75},"passingAttributes":{"vision":73,"crossing":72,"freeKickAccuracy":65,"shortPassing":78,"longPassing":76,"curve":78},"dribblingAttributes":{"agility":72,"balance":76,"reactions":69,"ballControl":77,"dribbling":74,"composure":73},"defendingAttributes":{"interceptions":59,"headingAccuracy":48,"standingTackle":56,"slidingTackle":51,"defenseAwareness":50},"physicalityAttributes":{"jumping":53,"stamina":71,"strength":39,"aggression":58},"goalkeeperAttributes":{"diving":null,"handling":null,"kicking":null,"positioning":null,"reflexes":null,"speed":62}},{"id":13025,"resourceId":215703,"resourceBaseId":215703,"futBinId":30567,"futWizId":8447,"firstName":"Marlon","lastName":"da Silva Barbosa","name":"Marlon da Silva Barbosa","commonName":"Marlon","height":182,"weight":0,"birthDate":"1995-09-07","age":27,"league":31,"nation":54,"club":111811,"rarity":1,"traits":[],"specialities":[],"position":"CB","skillMoves":3,"weakFoot":3,"foot":"Right","attackWorkRate":"Med","defenseWorkRate":"Med","totalStats":386,"totalStatsInGame":1784,"color":"silver","rating":73,"ratingAverage":64,"pace":66,"shooting":44,"passing":59,"dribbling":66,"defending":74,"physicality":77,"paceAttributes":{"acceleration":63,"sprintSpeed":69},"shootingAttributes":{"positioning":36,"finishing":40,"shotPower":61,"longShots":36,"volleys":33,"penalties":58},"passingAttributes":{"vision":51,"crossing":43,"freeKickAccuracy":46,"shortPassing":70,"longPassing":69,"curve":57},"dribblingAttributes":{"agility":63,"balance":63,"reactions":67,"ballControl":71,"dribbling":64,"composure":68},"defendingAttributes":{"interceptions":73,"headingAccuracy":71,"standingTackle":73,"slidingTackle":74,"defenseAwareness":75},"physicalityAttributes":{"jumping":61,"stamina":69,"strength":83,"aggression":77},"goalkeeperAttributes":{"diving":null,"handling":null,"kicking":null,"positioning":null,"reflexes":null,"speed":66}},{"id":13026,"resourceId":50586649,"resourceBaseId":255001,"futBinId":38323,"futWizId":8284,"firstName":"Nicolò","lastName":"Rovella","name":"Nicolò Rovella","commonName":"Rovella","height":179,"weight":70,"birthDate":"2001-12-04","age":21,"league":31,"nation":27,"club":111811,"rarity":1,"traits":[],"specialities":[],"position":"CM","skillMoves":3,"weakFoot":4,"foot":"Right","attackWorkRate":"Med","defenseWorkRate":"Med","totalStats":406,"totalStatsInGame":1963,"color":"silver","rating":73,"ratingAverage":67,"pace":72,"shooting":53,"passing":73,"dribbling":76,"defending":68,"physicality":64,"paceAttributes":{"acceleration":69,"sprintSpeed":75},"shootingAttributes":{"positioning":60,"finishing":46,"shotPower":66,"longShots":53,"volleys":60,"penalties":56},"passingAttributes":{"vision":76,"crossing":65,"freeKickAccuracy":71,"shortPassing":77,"longPassing":73,"curve":67},"dribblingAttributes":{"agility":77,"balance":77,"reactions":72,"ballControl":77,"dribbling":75,"composure":72},"defendingAttributes":{"interceptions":70,"headingAccuracy":48,"standingTackle":72,"slidingTackle":69,"defenseAwareness":69},"physicalityAttributes":{"jumping":67,"stamina":83,"strength":53,"aggression":68},"goalkeeperAttributes":{"diving":null,"handling":null,"kicking":null,"positioning":null,"reflexes":null,"speed":72}},{"id":13027,"resourceId":201285,"resourceBaseId":201285,"futBinId":29177,"futWizId":8523,"firstName":"Christian","lastName":"Gytkjær","name":"Christian Gytkjær","commonName":"Gytkjær","height":185,"weight":0,"birthDate":"1990-05-06","age":32,"league":31,"nation":13,"club":111811,"rarity":1,"traits":[],"specialities":[],"position":"ST","skillMoves":3,"weakFoot":4,"foot":"Right","attackWorkRate":"Med","defenseWorkRate":"Med","totalStats":376,"totalStatsInGame":1813,"color":"silver","rating":73,"ratingAverage":62,"pace":71,"shooting":74,"passing":57,"dribbling":69,"defending":33,"physicality":72,"paceAttributes":{"acceleration":68,"sprintSpeed":73},"shootingAttributes":{"positioning":76,"finishing":74,"shotPower":77,"longShots":70,"volleys":67,"penalties":76},"passingAttributes":{"vision":61,"crossing":51,"freeKickAccuracy":55,"shortPassing":62,"longPassing":45,"curve":61},"dribblingAttributes":{"agility":70,"balance":68,"reactions":74,"ballControl":73,"dribbling":66,"composure":75},"defendingAttributes":{"interceptions":32,"headingAccuracy":72,"standingTackle":16,"slidingTackle":19,"defenseAwareness":42},"physicalityAttributes":{"jumping":81,"stamina":64,"strength":78,"aggression":67},"goalkeeperAttributes":{"diving":null,"handling":null,"kicking":null,"positioning":null,"reflexes":null,"speed":70}},{"id":13300,"resourceId":50573915,"resourceBaseId":242267,"futBinId":38202,"futWizId":8127,"firstName":"Jorman","lastName":"Campuzano","name":"Jorman Campuzano","commonName":"Campuzano","height":175,"weight":0,"birthDate":"1996-04-30","age":26,"league":68,"nation":56,"club":112120,"rarity":1,"traits":[],"specialities":[],"position":"CDM","skillMoves":2,"weakFoot":3,"foot":"Right","attackWorkRate":"Low","defenseWorkRate":"High","totalStats":381,"totalStatsInGame":1769,"color":"silver","rating":73,"ratingAverage":63,"pace":72,"shooting":40,"passing":60,"dribbling":65,"defending":72,"physicality":72,"paceAttributes":{"acceleration":74,"sprintSpeed":71},"shootingAttributes":{"positioning":35,"finishing":30,"shotPower":56,"longShots":47,"volleys":42,"penalties":36},"passingAttributes":{"vision":67,"crossing":36,"freeKickAccuracy":41,"shortPassing":72,"longPassing":69,"curve":38},"dribblingAttributes":{"agility":73,"balance":73,"reactions":70,"ballControl":67,"dribbling":59,"composure":68},"defendingAttributes":{"interceptions":73,"headingAccuracy":57,"standingTackle":74,"slidingTackle":74,"defenseAwareness":72},"physicalityAttributes":{"jumping":73,"stamina":80,"strength":66,"aggression":76},"goalkeeperAttributes":{"diving":null,"handling":null,"kicking":null,"positioning":null,"reflexes":null,"speed":72}},{"id":13045,"resourceId":192242,"resourceBaseId":192242,"futBinId":44339,"futWizId":8311,"firstName":"Paul","lastName":"Lasne","name":"Paul Lasne","commonName":"Lasne","height":186,"weight":0,"birthDate":"1989-01-16","age":34,"league":17,"nation":18,"club":111817,"rarity":1,"traits":[],"specialities":[],"position":"CDM","skillMoves":3,"weakFoot":4,"foot":"Left","attackWorkRate":"Med","defenseWorkRate":"High","totalStats":390,"totalStatsInGame":1931,"color":"silver","rating":73,"ratingAverage":65,"pace":44,"shooting":63,"passing":72,"dribbling":70,"defending":70,"physicality":71,"paceAttributes":{"acceleration":52,"sprintSpeed":38},"shootingAttributes":{"positioning":64,"finishing":55,"shotPower":74,"longShots":69,"volleys":69,"penalties":59},"passingAttributes":{"vision":72,"crossing":69,"freeKickAccuracy":60,"shortPassing":75,"longPassing":74,"curve":72},"dribblingAttributes":{"agility":60,"balance":62,"reactions":69,"ballControl":72,"dribbling":71,"composure":69},"defendingAttributes":{"interceptions":70,"headingAccuracy":64,"standingTackle":72,"slidingTackle":71,"defenseAwareness":70},"physicalityAttributes":{"jumping":68,"stamina":66,"strength":74,"aggression":71},"goalkeeperAttributes":{"diving":null,"handling":null,"kicking":null,"positioning":null,"reflexes":null,"speed":45}}]}